{
"meta":{"test_sets":[],"test_metrics":[],"learn_metrics":[{"best_value":"Min","name":"RMSE"}],"launch_mode":"Train","parameters":"","iteration_count":1000,"learn_sets":["learn"],"name":"experiment"},
"iterations":[
{"learn":[1.000644585],"iteration":0,"passed_time":0.002323911995,"remaining_time":2.321588083},
{"learn":[0.9876916493],"iteration":1,"passed_time":0.004302845084,"remaining_time":2.147119697},
{"learn":[0.9736707802],"iteration":2,"passed_time":0.005519227132,"remaining_time":1.83422315},
{"learn":[0.9608188095],"iteration":3,"passed_time":0.006512027184,"remaining_time":1.621494769},
{"learn":[0.947486961],"iteration":4,"passed_time":0.007761261232,"remaining_time":1.544490985},
{"learn":[0.9358356892],"iteration":5,"passed_time":0.008835150562,"remaining_time":1.463689943},
{"learn":[0.9261741031],"iteration":6,"passed_time":0.009580886427,"remaining_time":1.359117175},
{"learn":[0.9161210986],"iteration":7,"passed_time":0.0107792909,"remaining_time":1.336632072},
{"learn":[0.9062925305],"iteration":8,"passed_time":0.01196158187,"remaining_time":1.31710307},
{"learn":[0.8980626481],"iteration":9,"passed_time":0.01302396923,"remaining_time":1.289372953},
{"learn":[0.8885108357],"iteration":10,"passed_time":0.01429383231,"remaining_time":1.285145469},
{"learn":[0.8786232087],"iteration":11,"passed_time":0.01544987308,"remaining_time":1.27203955},
{"learn":[0.8694765623],"iteration":12,"passed_time":0.01654614017,"remaining_time":1.256233873},
{"learn":[0.8620138024],"iteration":13,"passed_time":0.01765658667,"remaining_time":1.243528176},
{"learn":[0.8545440856],"iteration":14,"passed_time":0.0187528272,"remaining_time":1.231435653},
{"learn":[0.8477996917],"iteration":15,"passed_time":0.01980211059,"remaining_time":1.217829801},
{"learn":[0.8418975685],"iteration":16,"passed_time":0.02088280823,"remaining_time":1.207517676},
{"learn":[0.8340044765],"iteration":17,"passed_time":0.02199399504,"remaining_time":1.199894619},
{"learn":[0.8270378682],"iteration":18,"passed_time":0.02308571642,"remaining_time":1.19195199},
{"learn":[0.820531349],"iteration":19,"passed_time":0.02412698623,"remaining_time":1.182222325},
{"learn":[0.8142336875],"iteration":20,"passed_time":0.02517815844,"remaining_time":1.173781767},
{"learn":[0.8077396244],"iteration":21,"passed_time":0.02621557453,"remaining_time":1.16540145},
{"learn":[0.8034756091],"iteration":22,"passed_time":0.02721970748,"remaining_time":1.156245835},
{"learn":[0.7996977615],"iteration":23,"passed_time":0.02826770831,"remaining_time":1.149553471},
{"learn":[0.7952888474],"iteration":24,"passed_time":0.02936075572,"remaining_time":1.145069473},
{"learn":[0.7911202651],"iteration":25,"passed_time":0.03049311382,"remaining_time":1.142318956},
{"learn":[0.7868234272],"iteration":26,"passed_time":0.03153740586,"remaining_time":1.136514663},
{"learn":[0.7822790832],"iteration":27,"passed_time":0.0325480603,"remaining_time":1.129882665},
{"learn":[0.7776526372],"iteration":28,"passed_time":0.03358148379,"remaining_time":1.124400716},
{"learn":[0.7734080571],"iteration":29,"passed_time":0.03456203914,"remaining_time":1.117505932},
{"learn":[0.7700708285],"iteration":30,"passed_time":0.03555059117,"remaining_time":1.111242672},
{"learn":[0.7671049516],"iteration":31,"passed_time":0.03657385804,"remaining_time":1.106359206},
{"learn":[0.7632952158],"iteration":32,"passed_time":0.03762657427,"remaining_time":1.102572646},
{"learn":[0.7596681282],"iteration":33,"passed_time":0.03863342995,"remaining_time":1.097643921},
{"learn":[0.7564493063],"iteration":34,"passed_time":0.03972880396,"remaining_time":1.095379881},
{"learn":[0.7525572488],"iteration":35,"passed_time":0.04079498887,"remaining_time":1.092399147},
{"learn":[0.749427027],"iteration":36,"passed_time":0.04185357686,"remaining_time":1.089324176},
{"learn":[0.7462341739],"iteration":37,"passed_time":0.04288640013,"remaining_time":1.085703077},
{"learn":[0.7426354912],"iteration":38,"passed_time":0.04435877296,"remaining_time":1.093045662},
{"learn":[0.7409559934],"iteration":39,"passed_time":0.04492238055,"remaining_time":1.078137133},
{"learn":[0.7376363157],"iteration":40,"passed_time":0.04593555301,"remaining_time":1.074443789},
{"learn":[0.7349274307],"iteration":41,"passed_time":0.04701612807,"remaining_time":1.072415493},
{"learn":[0.7322359282],"iteration":42,"passed_time":0.04805108351,"remaining_time":1.069415975},
{"learn":[0.7301936148],"iteration":43,"passed_time":0.0491051771,"remaining_time":1.066921575},
{"learn":[0.727592568],"iteration":44,"passed_time":0.0501199588,"remaining_time":1.063656903},
{"learn":[0.7250051995],"iteration":45,"passed_time":0.05114507645,"remaining_time":1.060704412},
{"learn":[0.721285165],"iteration":46,"passed_time":0.05218484028,"remaining_time":1.05813091},
{"learn":[0.7192446406],"iteration":47,"passed_time":0.05322004812,"remaining_time":1.055530954},
{"learn":[0.71685418],"iteration":48,"passed_time":0.05430907153,"remaining_time":1.054039327},
{"learn":[0.7158760596],"iteration":49,"passed_time":0.05473893667,"remaining_time":1.040039797},
{"learn":[0.7132865386],"iteration":50,"passed_time":0.05552786895,"remaining_time":1.033253875},
{"learn":[0.712169399],"iteration":51,"passed_time":0.05656064874,"remaining_time":1.031144135},
{"learn":[0.7105657075],"iteration":52,"passed_time":0.05766476215,"remaining_time":1.030349618},
{"learn":[0.7071875351],"iteration":53,"passed_time":0.05876243439,"remaining_time":1.029430795},
{"learn":[0.7060336934],"iteration":54,"passed_time":0.05982917544,"remaining_time":1.027974014},
{"learn":[0.7032750412],"iteration":55,"passed_time":0.06088761911,"remaining_time":1.026391294},
{"learn":[0.7016821149],"iteration":56,"passed_time":0.06187711071,"remaining_time":1.023686235},
{"learn":[0.7006121607],"iteration":57,"passed_time":0.06268785193,"remaining_time":1.018137181},
{"learn":[0.6989782081],"iteration":58,"passed_time":0.06374453721,"remaining_time":1.016671348},
{"learn":[0.6974912734],"iteration":59,"passed_time":0.06443631863,"remaining_time":1.009502325},
{"learn":[0.6965079244],"iteration":60,"passed_time":0.06544021185,"remaining_time":1.007350146},
{"learn":[0.6947639648],"iteration":61,"passed_time":0.06643814576,"remaining_time":1.00514485},
{"learn":[0.6924387874],"iteration":62,"passed_time":0.06752933757,"remaining_time":1.00436491},
{"learn":[0.691028152],"iteration":63,"passed_time":0.06848834423,"remaining_time":1.001642034},
{"learn":[0.6900407851],"iteration":64,"passed_time":0.06956120099,"remaining_time":1.000611122},
{"learn":[0.6884861455],"iteration":65,"passed_time":0.07053624569,"remaining_time":0.9981947496},
{"learn":[0.6872640642],"iteration":66,"passed_time":0.07156519471,"remaining_time":0.9965720398},
{"learn":[0.6850918287],"iteration":67,"passed_time":0.07259571614,"remaining_time":0.9949883448},
{"learn":[0.6842029726],"iteration":68,"passed_time":0.07329941981,"remaining_time":0.9890110122},
{"learn":[0.6825156238],"iteration":69,"passed_time":0.07416426583,"remaining_time":0.9853252461},
{"learn":[0.68114585],"iteration":70,"passed_time":0.0751926714,"remaining_time":0.9838590385},
{"learn":[0.6797856977],"iteration":71,"passed_time":0.07622445546,"remaining_time":0.9824485371},
{"learn":[0.6777998068],"iteration":72,"passed_time":0.07728166669,"remaining_time":0.9813713017},
{"learn":[0.6757467674],"iteration":73,"passed_time":0.07832118838,"remaining_time":0.9800732492},
{"learn":[0.6742393738],"iteration":74,"passed_time":0.07937772089,"remaining_time":0.9789918909},
{"learn":[0.6729983308],"iteration":75,"passed_time":0.08046418522,"remaining_time":0.978275094},
{"learn":[0.6719334832],"iteration":76,"passed_time":0.08142334586,"remaining_time":0.9760227043},
{"learn":[0.6705881788],"iteration":77,"passed_time":0.08244175423,"remaining_time":0.9745038128},
{"learn":[0.6695493186],"iteration":78,"passed_time":0.08344725186,"remaining_time":0.9728470755},
{"learn":[0.6684621428],"iteration":79,"passed_time":0.0844775233,"remaining_time":0.9714915179},
{"learn":[0.6674964096],"iteration":80,"passed_time":0.08552805724,"remaining_time":0.9703738841},
{"learn":[0.6655823655],"iteration":81,"passed_time":0.08657747288,"remaining_time":0.9692453671},
{"learn":[0.6643280721],"iteration":82,"passed_time":0.08762370385,"remaining_time":0.9680835714},
{"learn":[0.6620099316],"iteration":83,"passed_time":0.08866161086,"remaining_time":0.9668337566},
{"learn":[0.6604527204],"iteration":84,"passed_time":0.08971631071,"remaining_time":0.9657696977},
{"learn":[0.6593841634],"iteration":85,"passed_time":0.09072348219,"remaining_time":0.9642007294},
{"learn":[0.6590523609],"iteration":86,"passed_time":0.09173354064,"remaining_time":0.9626749725},
{"learn":[0.6580022245],"iteration":87,"passed_time":0.09301650528,"remaining_time":0.9639892365},
{"learn":[0.6566920848],"iteration":88,"passed_time":0.09405360858,"remaining_time":0.9627285103},
{"learn":[0.655280299],"iteration":89,"passed_time":0.09506686256,"remaining_time":0.9612316103},
{"learn":[0.6544847501],"iteration":90,"passed_time":0.09612259196,"remaining_time":0.9601696273},
{"learn":[0.6535339834],"iteration":91,"passed_time":0.09713482725,"remaining_time":0.9586785124},
{"learn":[0.6522533544],"iteration":92,"passed_time":0.09816839265,"remaining_time":0.9574057218},
{"learn":[0.651007182],"iteration":93,"passed_time":0.09916720938,"remaining_time":0.9558031031},
{"learn":[0.6498613344],"iteration":94,"passed_time":0.09998181699,"remaining_time":0.9524583619},
{"learn":[0.6481915741],"iteration":95,"passed_time":0.1008404742,"remaining_time":0.9495811325},
{"learn":[0.6472264548],"iteration":96,"passed_time":0.1016741029,"remaining_time":0.9465125247},
{"learn":[0.6459362141],"iteration":97,"passed_time":0.1024753197,"remaining_time":0.9431912079},
{"learn":[0.6446377118],"iteration":98,"passed_time":0.103368309,"remaining_time":0.9407560241},
{"learn":[0.6431531491],"iteration":99,"passed_time":0.1041288565,"remaining_time":0.9371597082},
{"learn":[0.6414741092],"iteration":100,"passed_time":0.1048886938,"remaining_time":0.9336132254},
{"learn":[0.6403827431],"iteration":101,"passed_time":0.1057317327,"remaining_time":0.9308538823},
{"learn":[0.6389346394],"iteration":102,"passed_time":0.1065038468,"remaining_time":0.9275140834},
{"learn":[0.6377772161],"iteration":103,"passed_time":0.107257429,"remaining_time":0.9240640036},
{"learn":[0.6366350426],"iteration":104,"passed_time":0.1080376098,"remaining_time":0.9208920073},
{"learn":[0.6360782781],"iteration":105,"passed_time":0.1088081998,"remaining_time":0.9176842509},
{"learn":[0.6348518816],"iteration":106,"passed_time":0.1096001645,"remaining_time":0.9147004387},
{"learn":[0.633613199],"iteration":107,"passed_time":0.1103706036,"remaining_time":0.9115794294},
{"learn":[0.6328868492],"iteration":108,"passed_time":0.1111330894,"remaining_time":0.908436538},
{"learn":[0.63160886],"iteration":109,"passed_time":0.1119588572,"remaining_time":0.9058489356},
{"learn":[0.6305089763],"iteration":110,"passed_time":0.1127376745,"remaining_time":0.902917051},
{"learn":[0.629210628],"iteration":111,"passed_time":0.1135164417,"remaining_time":0.9000232166},
{"learn":[0.6284238781],"iteration":112,"passed_time":0.1143221831,"remaining_time":0.8973785527},
{"learn":[0.6275103821],"iteration":113,"passed_time":0.1151286588,"remaining_time":0.8947718572},
{"learn":[0.6261479191],"iteration":114,"passed_time":0.1159590907,"remaining_time":0.8923808286},
{"learn":[0.6250690473],"iteration":115,"passed_time":0.1171208511,"remaining_time":0.8925416582},
{"learn":[0.6244749809],"iteration":116,"passed_time":0.1180971391,"remaining_time":0.891280118},
{"learn":[0.6236349806],"iteration":117,"passed_time":0.1191446146,"remaining_time":0.8905555089},
{"learn":[0.6228716599],"iteration":118,"passed_time":0.1201941002,"remaining_time":0.8898403556},
{"learn":[0.6217281006],"iteration":119,"passed_time":0.121233064,"remaining_time":0.8890424692},
{"learn":[0.6211429747],"iteration":120,"passed_time":0.1222426695,"remaining_time":0.8880273267},
{"learn":[0.6202962576],"iteration":121,"passed_time":0.1232979171,"remaining_time":0.8873407475},
{"learn":[0.6195304008],"iteration":122,"passed_time":0.1243210584,"remaining_time":0.8864192535},
{"learn":[0.6185331486],"iteration":123,"passed_time":0.1253093356,"remaining_time":0.8852498227},
{"learn":[0.6176852554],"iteration":124,"passed_time":0.1263531168,"remaining_time":0.8844718178},
{"learn":[0.6165599818],"iteration":125,"passed_time":0.1273638256,"remaining_time":0.8834601872},
{"learn":[0.615969005],"iteration":126,"passed_time":0.1284573706,"remaining_time":0.8830179884},
{"learn":[0.6152902248],"iteration":127,"passed_time":0.1295037918,"remaining_time":0.8822445814},
{"learn":[0.614380497],"iteration":128,"passed_time":0.1305603629,"remaining_time":0.8815354737},
{"learn":[0.613998417],"iteration":129,"passed_time":0.1312353841,"remaining_time":0.8782675706},
{"learn":[0.6132452391],"iteration":130,"passed_time":0.1322595362,"remaining_time":0.8773552441},
{"learn":[0.6129456123],"iteration":131,"passed_time":0.1332576465,"remaining_time":0.8762699782},
{"learn":[0.6115176294],"iteration":132,"passed_time":0.1342786477,"remaining_time":0.8753352449},
{"learn":[0.6104953667],"iteration":133,"passed_time":0.1352907852,"remaining_time":0.8743419401},
{"learn":[0.6085500057],"iteration":134,"passed_time":0.1363576361,"remaining_time":0.8736989279},
{"learn":[0.6075362713],"iteration":135,"passed_time":0.137401683,"remaining_time":0.8729048098},
{"learn":[0.6068233702],"iteration":136,"passed_time":0.1384501343,"remaining_time":0.8721347877},
{"learn":[0.6062150624],"iteration":137,"passed_time":0.1395056777,"remaining_time":0.8714050305},
{"learn":[0.605210864],"iteration":138,"passed_time":0.1405502977,"remaining_time":0.8706029229},
{"learn":[0.6044591027],"iteration":139,"passed_time":0.1416225639,"remaining_time":0.869967178},
{"learn":[0.6038901609],"iteration":140,"passed_time":0.1426745784,"remaining_time":0.8692018643},
{"learn":[0.6033644556],"iteration":141,"passed_time":0.1437217218,"remaining_time":0.8684030796},
{"learn":[0.602535849],"iteration":142,"passed_time":0.1447072691,"remaining_time":0.8672316757},
{"learn":[0.60150915],"iteration":143,"passed_time":0.1457588779,"remaining_time":0.8664555519},
{"learn":[0.6006638038],"iteration":144,"passed_time":0.1467967058,"remaining_time":0.8655943687},
{"learn":[0.6000656794],"iteration":145,"passed_time":0.1478599506,"remaining_time":0.8648794372},
{"learn":[0.5991951906],"iteration":146,"passed_time":0.148882726,"remaining_time":0.8639249337},
{"learn":[0.5983597147],"iteration":147,"passed_time":0.1499221184,"remaining_time":0.8630651683},
{"learn":[0.5973108569],"iteration":148,"passed_time":0.1509575274,"remaining_time":0.8621802401},
{"learn":[0.5958570894],"iteration":149,"passed_time":0.1520248143,"remaining_time":0.8614739476},
{"learn":[0.5941604299],"iteration":150,"passed_time":0.1530479169,"remaining_time":0.8605144468},
{"learn":[0.5938337316],"iteration":151,"passed_time":0.1540666133,"remaining_time":0.8595295269},
{"learn":[0.5928754408],"iteration":152,"passed_time":0.1554679532,"remaining_time":0.8606624601},
{"learn":[0.5921592062],"iteration":153,"passed_time":0.1565042148,"remaining_time":0.8597569202},
{"learn":[0.5913555038],"iteration":154,"passed_time":0.1575191299,"remaining_time":0.8587333213},
{"learn":[0.590459895],"iteration":155,"passed_time":0.1585496755,"remaining_time":0.8577943983},
{"learn":[0.5892854738],"iteration":156,"passed_time":0.1595962495,"remaining_time":0.8569403714},
{"learn":[0.5885496009],"iteration":157,"passed_time":0.1606633094,"remaining_time":0.856193079},
{"learn":[0.5878613686],"iteration":158,"passed_time":0.1617298662,"remaining_time":0.8554391038},
{"learn":[0.5871411373],"iteration":159,"passed_time":0.1627632094,"remaining_time":0.8545068494},
{"learn":[0.586698733],"iteration":160,"passed_time":0.1637778299,"remaining_time":0.8534757719},
{"learn":[0.5854891125],"iteration":161,"passed_time":0.164833633,"remaining_time":0.8526579285},
{"learn":[0.584147348],"iteration":162,"passed_time":0.1658709126,"remaining_time":0.851742048},
{"learn":[0.5829548056],"iteration":163,"passed_time":0.1668872323,"remaining_time":0.8507178425},
{"learn":[0.5819282172],"iteration":164,"passed_time":0.1680401971,"remaining_time":0.8503852396},
{"learn":[0.5814256983],"iteration":165,"passed_time":0.1691012952,"remaining_time":0.8495812061},
{"learn":[0.5800658094],"iteration":166,"passed_time":0.1701277667,"remaining_time":0.8486013751},
{"learn":[0.5787877793],"iteration":167,"passed_time":0.1711316792,"remaining_time":0.8475092685},
{"learn":[0.577678616],"iteration":168,"passed_time":0.1721886821,"remaining_time":0.8466792594},
{"learn":[0.5768212258],"iteration":169,"passed_time":0.1732250373,"remaining_time":0.8457457702},
{"learn":[0.5754246025],"iteration":170,"passed_time":0.1742819194,"remaining_time":0.8449105917},
{"learn":[0.5751895165],"iteration":171,"passed_time":0.1753342751,"remaining_time":0.8440510454},
{"learn":[0.5741837583],"iteration":172,"passed_time":0.1763654179,"remaining_time":0.8430878648},
{"learn":[0.5736658858],"iteration":173,"passed_time":0.177381763,"remaining_time":0.8420536563},
{"learn":[0.5729939547],"iteration":174,"passed_time":0.1784236179,"remaining_time":0.8411399129},
{"learn":[0.5718476727],"iteration":175,"passed_time":0.1794688145,"remaining_time":0.8402403587},
{"learn":[0.5715226792],"iteration":176,"passed_time":0.1803259772,"remaining_time":0.8384648546},
{"learn":[0.5706474189],"iteration":177,"passed_time":0.1813871213,"remaining_time":0.8376416499},
{"learn":[0.5699154505],"iteration":178,"passed_time":0.1824987893,"remaining_time":0.8370475199},
{"learn":[0.5689167286],"iteration":179,"passed_time":0.1836316124,"remaining_time":0.8365440121},
{"learn":[0.5676537772],"iteration":180,"passed_time":0.1846666826,"remaining_time":0.8355912322},
{"learn":[0.5670847614],"iteration":181,"passed_time":0.1857246885,"remaining_time":0.8347406327},
{"learn":[0.5663596797],"iteration":182,"passed_time":0.1867597725,"remaining_time":0.8337854325},
{"learn":[0.5652940575],"iteration":183,"passed_time":0.18783384,"remaining_time":0.8330022468},
{"learn":[0.5645455695],"iteration":184,"passed_time":0.1888901678,"remaining_time":0.8321377662},
{"learn":[0.5642030572],"iteration":185,"passed_time":0.189886888,"remaining_time":0.8310103592},
{"learn":[0.5632108469],"iteration":186,"passed_time":0.1909533893,"remaining_time":0.83018773},
{"learn":[0.5620345978],"iteration":187,"passed_time":0.192000674,"remaining_time":0.8292795067},
{"learn":[0.5613560504],"iteration":188,"passed_time":0.1930474707,"remaining_time":0.8283677184},
{"learn":[0.5606169165],"iteration":189,"passed_time":0.1941044296,"remaining_time":0.8274978313},
{"learn":[0.5596570154],"iteration":190,"passed_time":0.195175281,"remaining_time":0.8266848288},
{"learn":[0.5584301871],"iteration":191,"passed_time":0.1962458027,"remaining_time":0.8258677529},
{"learn":[0.5574221457],"iteration":192,"passed_time":0.1973157658,"remaining_time":0.8250457151},
{"learn":[0.5566832537],"iteration":193,"passed_time":0.1983528232,"remaining_time":0.82408441},
{"learn":[0.5556766196],"iteration":194,"passed_time":0.1993929071,"remaining_time":0.8231348216},
{"learn":[0.5546918124],"iteration":195,"passed_time":0.2004505996,"remaining_time":0.8222565412},
{"learn":[0.5536048085],"iteration":196,"passed_time":0.2014569577,"remaining_time":0.8211671931},
{"learn":[0.5528668372],"iteration":197,"passed_time":0.2025056813,"remaining_time":0.820250285},
{"learn":[0.5514496217],"iteration":198,"passed_time":0.2035664274,"remaining_time":0.8193804441},
{"learn":[0.5507807503],"iteration":199,"passed_time":0.2046285322,"remaining_time":0.8185141288},
{"learn":[0.5500208678],"iteration":200,"passed_time":0.2056496573,"remaining_time":0.8174829659},
{"learn":[0.5493123144],"iteration":201,"passed_time":0.2066888323,"remaining_time":0.8165232089},
{"learn":[0.5481459043],"iteration":202,"passed_time":0.207755484,"remaining_time":0.8156705456},
{"learn":[0.5478535394],"iteration":203,"passed_time":0.2088016009,"remaining_time":0.8147356583},
{"learn":[0.5470908877],"iteration":204,"passed_time":0.2098602637,"remaining_time":0.8138483398},
{"learn":[0.5464351711],"iteration":205,"passed_time":0.2109195673,"remaining_time":0.8129618272},
{"learn":[0.5451952507],"iteration":206,"passed_time":0.2119728759,"remaining_time":0.812050679},
{"learn":[0.5446810786],"iteration":207,"passed_time":0.2130282079,"remaining_time":0.8111458687},
{"learn":[0.5440577574],"iteration":208,"passed_time":0.2140468252,"remaining_time":0.8101006639},
{"learn":[0.5429125971],"iteration":209,"passed_time":0.2150613992,"remaining_time":0.8090405018},
{"learn":[0.5419867069],"iteration":210,"passed_time":0.216068462,"remaining_time":0.8079526849},
{"learn":[0.5413195896],"iteration":211,"passed_time":0.2170948924,"remaining_time":0.8069376189},
{"learn":[0.5402296864],"iteration":212,"passed_time":0.2181299306,"remaining_time":0.8059542505},
{"learn":[0.5388671387],"iteration":213,"passed_time":0.2191802586,"remaining_time":0.8050265573},
{"learn":[0.5379354569],"iteration":214,"passed_time":0.2202242252,"remaining_time":0.8040744965},
{"learn":[0.536974011],"iteration":215,"passed_time":0.2212419512,"remaining_time":0.8030263414},
{"learn":[0.5361060638],"iteration":216,"passed_time":0.2222698912,"remaining_time":0.8020153217},
{"learn":[0.5352919124],"iteration":217,"passed_time":0.2233009042,"remaining_time":0.80101517},
{"learn":[0.53429325],"iteration":218,"passed_time":0.2243401819,"remaining_time":0.8000442103},
{"learn":[0.5332643575],"iteration":219,"passed_time":0.2253801559,"remaining_time":0.799075098},
{"learn":[0.5321377751],"iteration":220,"passed_time":0.2264063737,"remaining_time":0.7980568557},
{"learn":[0.5307746144],"iteration":221,"passed_time":0.2274342135,"remaining_time":0.7970442256},
{"learn":[0.5293430596],"iteration":222,"passed_time":0.2284719122,"remaining_time":0.7960658106},
{"learn":[0.528281176],"iteration":223,"passed_time":0.2295396991,"remaining_time":0.7951911004},
{"learn":[0.5275500679],"iteration":224,"passed_time":0.2305328596,"remaining_time":0.7940576276},
{"learn":[0.5262848549],"iteration":225,"passed_time":0.2315764361,"remaining_time":0.7930980599},
{"learn":[0.5251631205],"iteration":226,"passed_time":0.2326329656,"remaining_time":0.7921818608},
{"learn":[0.5246889734],"iteration":227,"passed_time":0.2336553327,"remaining_time":0.7911487582},
{"learn":[0.5241628177],"iteration":228,"passed_time":0.2347062405,"remaining_time":0.7902118402},
{"learn":[0.5230132836],"iteration":229,"passed_time":0.235749474,"remaining_time":0.789248239},
{"learn":[0.5219173969],"iteration":230,"passed_time":0.2368130298,"remaining_time":0.7883516012},
{"learn":[0.5209916408],"iteration":231,"passed_time":0.2378873502,"remaining_time":0.7874891594},
{"learn":[0.5200445476],"iteration":232,"passed_time":0.2389476809,"remaining_time":0.7865788466},
{"learn":[0.5191849197],"iteration":233,"passed_time":0.2400128496,"remaining_time":0.7856830887},
{"learn":[0.5185082222],"iteration":234,"passed_time":0.2410714454,"remaining_time":0.7847644924},
{"learn":[0.5178257119],"iteration":235,"passed_time":0.242089765,"remaining_time":0.783714324},
{"learn":[0.5168036908],"iteration":236,"passed_time":0.2431054905,"remaining_time":0.7826560728},
{"learn":[0.5159881655],"iteration":237,"passed_time":0.2441349395,"remaining_time":0.7816421172},
{"learn":[0.5153830293],"iteration":238,"passed_time":0.2451575693,"remaining_time":0.7806063191},
{"learn":[0.5146190444],"iteration":239,"passed_time":0.246216295,"remaining_time":0.7796849341},
{"learn":[0.5137853748],"iteration":240,"passed_time":0.2472309734,"remaining_time":0.7786236881},
{"learn":[0.5133188685],"iteration":241,"passed_time":0.2482981589,"remaining_time":0.7777272911},
{"learn":[0.5124706478],"iteration":242,"passed_time":0.2493434515,"remaining_time":0.7767612872},
{"learn":[0.5120073042],"iteration":243,"passed_time":0.2504042556,"remaining_time":0.7758426936},
{"learn":[0.5112069947],"iteration":244,"passed_time":0.2514249272,"remaining_time":0.7747992653},
{"learn":[0.5097454327],"iteration":245,"passed_time":0.2524794296,"remaining_time":0.773859715},
{"learn":[0.5090383153],"iteration":246,"passed_time":0.253576696,"remaining_time":0.7730496036},
{"learn":[0.508477308],"iteration":247,"passed_time":0.2546216988,"remaining_time":0.7720786995},
{"learn":[0.5075150224],"iteration":248,"passed_time":0.2556324069,"remaining_time":0.7710037655},
{"learn":[0.5070673576],"iteration":249,"passed_time":0.256680633,"remaining_time":0.770041899},
{"learn":[0.5063650296],"iteration":250,"passed_time":0.2577171584,"remaining_time":0.769044429},
{"learn":[0.5051619413],"iteration":251,"passed_time":0.2587658996,"remaining_time":0.7680829083},
{"learn":[0.5043255548],"iteration":252,"passed_time":0.2598194256,"remaining_time":0.7671348257},
{"learn":[0.5031221829],"iteration":253,"passed_time":0.2608965303,"remaining_time":0.7662551639},
{"learn":[0.5024543552],"iteration":254,"passed_time":0.2619199156,"remaining_time":0.7652170082},
{"learn":[0.5021526124],"iteration":255,"passed_time":0.2629338555,"remaining_time":0.7641515176},
{"learn":[0.5011198977],"iteration":256,"passed_time":0.2640067817,"remaining_time":0.7632569604},
{"learn":[0.500378287],"iteration":257,"passed_time":0.2650138976,"remaining_time":0.7621717521},
{"learn":[0.4995367786],"iteration":258,"passed_time":0.2660459232,"remaining_time":0.7611584136},
{"learn":[0.4987706114],"iteration":259,"passed_time":0.2670774114,"remaining_time":0.7601434017},
{"learn":[0.4978811339],"iteration":260,"passed_time":0.2681071189,"remaining_time":0.7591232216},
{"learn":[0.4966499107],"iteration":261,"passed_time":0.2691752053,"remaining_time":0.7582110744},
{"learn":[0.4957228798],"iteration":262,"passed_time":0.2701473697,"remaining_time":0.7570289408},
{"learn":[0.4952109944],"iteration":263,"passed_time":0.2711565604,"remaining_time":0.7559516229},
{"learn":[0.4943962058],"iteration":264,"passed_time":0.2721983525,"remaining_time":0.7549652419},
{"learn":[0.4936367988],"iteration":265,"passed_time":0.2732877207,"remaining_time":0.7541097256},
{"learn":[0.4928735335],"iteration":266,"passed_time":0.2742944967,"remaining_time":0.7530257156},
{"learn":[0.4919482683],"iteration":267,"passed_time":0.2753898804,"remaining_time":0.7521843001},
{"learn":[0.4915763864],"iteration":268,"passed_time":0.27644605,"remaining_time":0.7512344332},
{"learn":[0.4908760104],"iteration":269,"passed_time":0.2774217498,"remaining_time":0.7500662125},
{"learn":[0.4902152588],"iteration":270,"passed_time":0.2784665141,"remaining_time":0.7490851983},
{"learn":[0.4894933236],"iteration":271,"passed_time":0.2794732604,"remaining_time":0.7480019618},
{"learn":[0.488987258],"iteration":272,"passed_time":0.2805079484,"remaining_time":0.746993694},
{"learn":[0.4883539889],"iteration":273,"passed_time":0.2815770758,"remaining_time":0.7460764855},
{"learn":[0.4870481934],"iteration":274,"passed_time":0.2826783204,"remaining_time":0.7452428446},
{"learn":[0.486710784],"iteration":275,"passed_time":0.2837275965,"remaining_time":0.7442709416},
{"learn":[0.4860819264],"iteration":276,"passed_time":0.2847731711,"remaining_time":0.7432888185},
{"learn":[0.4849882716],"iteration":277,"passed_time":0.2858110491,"remaining_time":0.7422862499},
{"learn":[0.4842750717],"iteration":278,"passed_time":0.2868825781,"remaining_time":0.7413703899},
{"learn":[0.4839266756],"iteration":279,"passed_time":0.2879699711,"remaining_time":0.7404942114},
{"learn":[0.4833651471],"iteration":280,"passed_time":0.2890352031,"remaining_time":0.7395598258},
{"learn":[0.4826705152],"iteration":281,"passed_time":0.2900767924,"remaining_time":0.7385643154},
{"learn":[0.4818379079],"iteration":282,"passed_time":0.2911180984,"remaining_time":0.7375677617},
{"learn":[0.4812708682],"iteration":283,"passed_time":0.2921591569,"remaining_time":0.7365702688},
{"learn":[0.4803612917],"iteration":284,"passed_time":0.2931747846,"remaining_time":0.7355086701},
{"learn":[0.4794726648],"iteration":285,"passed_time":0.2942405263,"remaining_time":0.7345725026},
{"learn":[0.4788333607],"iteration":286,"passed_time":0.2953278613,"remaining_time":0.7336890771},
{"learn":[0.4782865887],"iteration":287,"passed_time":0.2964097153,"remaining_time":0.7327906851},
{"learn":[0.4780007024],"iteration":288,"passed_time":0.2974097259,"remaining_time":0.7316896716},
{"learn":[0.4772085402],"iteration":289,"passed_time":0.2984927634,"remaining_time":0.7307926276},
{"learn":[0.4767704784],"iteration":290,"passed_time":0.2995586416,"remaining_time":0.7298524978},
{"learn":[0.4759661194],"iteration":291,"passed_time":0.3006152302,"remaining_time":0.7288889829},
{"learn":[0.475183171],"iteration":292,"passed_time":0.3016117928,"remaining_time":0.7277799915},
{"learn":[0.4748962058],"iteration":293,"passed_time":0.3026512342,"remaining_time":0.7267747324},
{"learn":[0.4744667713],"iteration":294,"passed_time":0.3036706262,"remaining_time":0.725721327},
{"learn":[0.4736408288],"iteration":295,"passed_time":0.3047506162,"remaining_time":0.7248122763},
{"learn":[0.4731619159],"iteration":296,"passed_time":0.3057348205,"remaining_time":0.7236753496},
{"learn":[0.4721826253],"iteration":297,"passed_time":0.306763865,"remaining_time":0.7226450778},
{"learn":[0.4713667879],"iteration":298,"passed_time":0.3078146586,"remaining_time":0.7216658048},
{"learn":[0.4703648445],"iteration":299,"passed_time":0.3088685329,"remaining_time":0.7206932435},
{"learn":[0.4694509576],"iteration":300,"passed_time":0.309836782,"remaining_time":0.7195212978},
{"learn":[0.468707669],"iteration":301,"passed_time":0.3108325705,"remaining_time":0.7184143516},
{"learn":[0.4675737944],"iteration":302,"passed_time":0.3117976017,"remaining_time":0.7172373873},
{"learn":[0.4670295233],"iteration":303,"passed_time":0.313269393,"remaining_time":0.7172220313},
{"learn":[0.4663564052],"iteration":304,"passed_time":0.3143340393,"remaining_time":0.7162693683},
{"learn":[0.4657552459],"iteration":305,"passed_time":0.3153696614,"remaining_time":0.7152501471},
{"learn":[0.4650550352],"iteration":306,"passed_time":0.3164643331,"remaining_time":0.7143641136},
{"learn":[0.4640169857],"iteration":307,"passed_time":0.317508005,"remaining_time":0.7133621412},
{"learn":[0.4632652675],"iteration":308,"passed_time":0.318547947,"remaining_time":0.7123515578},
{"learn":[0.4624965248],"iteration":309,"passed_time":0.3195568684,"remaining_time":0.7112717394},
{"learn":[0.4619346497],"iteration":310,"passed_time":0.3205802718,"remaining_time":0.7102244606},
{"learn":[0.4609441105],"iteration":311,"passed_time":0.3215967992,"remaining_time":0.7091621725},
{"learn":[0.4600074857],"iteration":312,"passed_time":0.3226061904,"remaining_time":0.7080845137},
{"learn":[0.4593862472],"iteration":313,"passed_time":0.3236807971,"remaining_time":0.7071497668},
{"learn":[0.4583952611],"iteration":314,"passed_time":0.3246685212,"remaining_time":0.7060251969},
{"learn":[0.4577699203],"iteration":315,"passed_time":0.3257251986,"remaining_time":0.7050507464},
{"learn":[0.4569876164],"iteration":316,"passed_time":0.3267216664,"remaining_time":0.703946051},
{"learn":[0.4562956442],"iteration":317,"passed_time":0.3277473728,"remaining_time":0.702904743},
{"learn":[0.4555804109],"iteration":318,"passed_time":0.3287438074,"remaining_time":0.7018010434},
{"learn":[0.4550176578],"iteration":319,"passed_time":0.3297719412,"remaining_time":0.7007653751},
{"learn":[0.4540466058],"iteration":320,"passed_time":0.3307732536,"remaining_time":0.6996730194},
{"learn":[0.4531957858],"iteration":321,"passed_time":0.3318315669,"remaining_time":0.6987012495},
{"learn":[0.4525695631],"iteration":322,"passed_time":0.3329054858,"remaining_time":0.6977616529},
{"learn":[0.4520030475],"iteration":323,"passed_time":0.3339746368,"remaining_time":0.6968112792},
{"learn":[0.4508261934],"iteration":324,"passed_time":0.335017319,"remaining_time":0.695805201},
{"learn":[0.4501020742],"iteration":325,"passed_time":0.3361023534,"remaining_time":0.6948864607},
{"learn":[0.4494736905],"iteration":326,"passed_time":0.337163675,"remaining_time":0.6939178999},
{"learn":[0.4489526274],"iteration":327,"passed_time":0.3381788226,"remaining_time":0.6928541732},
{"learn":[0.4482084451],"iteration":328,"passed_time":0.33921324,"remaining_time":0.6918300427},
{"learn":[0.4478978523],"iteration":329,"passed_time":0.3402637788,"remaining_time":0.6908385812},
{"learn":[0.4470051745],"iteration":330,"passed_time":0.3413073601,"remaining_time":0.6898327007},
{"learn":[0.4460871805],"iteration":331,"passed_time":0.3423454145,"remaining_time":0.6888154725},
{"learn":[0.4454711319],"iteration":332,"passed_time":0.3433850292,"remaining_time":0.6878012446},
{"learn":[0.4446043854],"iteration":333,"passed_time":0.3444253727,"remaining_time":0.686788318},
{"learn":[0.4440754178],"iteration":334,"passed_time":0.3454293118,"remaining_time":0.6857029622},
{"learn":[0.4435884306],"iteration":335,"passed_time":0.3464897572,"remaining_time":0.6847297583},
{"learn":[0.4426396857],"iteration":336,"passed_time":0.3475126932,"remaining_time":0.683682242},
{"learn":[0.4418247346],"iteration":337,"passed_time":0.3485629789,"remaining_time":0.682688438},
{"learn":[0.4409728057],"iteration":338,"passed_time":0.3496348707,"remaining_time":0.6817364294},
{"learn":[0.4398496443],"iteration":339,"passed_time":0.3506882645,"remaining_time":0.6807478075},
{"learn":[0.4393776467],"iteration":340,"passed_time":0.3517490855,"remaining_time":0.6797731593},
{"learn":[0.4388791867],"iteration":341,"passed_time":0.3527924905,"remaining_time":0.6787644992},
{"learn":[0.4384923282],"iteration":342,"passed_time":0.3538457345,"remaining_time":0.6777744826},
{"learn":[0.4381529175],"iteration":343,"passed_time":0.3548284232,"remaining_time":0.6766495512},
{"learn":[0.4376928936],"iteration":344,"passed_time":0.3558115751,"remaining_time":0.6755263237},
{"learn":[0.4372495108],"iteration":345,"passed_time":0.3568433416,"remaining_time":0.674495796},
{"learn":[0.4366642786],"iteration":346,"passed_time":0.3578615417,"remaining_time":0.6734397311},
{"learn":[0.4356565997],"iteration":347,"passed_time":0.3588585221,"remaining_time":0.6723441276},
{"learn":[0.4351775857],"iteration":348,"passed_time":0.3599053382,"remaining_time":0.6713420492},
{"learn":[0.4344931907],"iteration":349,"passed_time":0.3609678161,"remaining_time":0.6703688014},
{"learn":[0.4337283563],"iteration":350,"passed_time":0.3619992663,"remaining_time":0.6693376747},
{"learn":[0.4332058421],"iteration":351,"passed_time":0.3630358309,"remaining_time":0.6683159615},
{"learn":[0.4322075326],"iteration":352,"passed_time":0.3640785168,"remaining_time":0.6673053834},
{"learn":[0.4312786036],"iteration":353,"passed_time":0.3651320403,"remaining_time":0.6663144013},
{"learn":[0.4303145647],"iteration":354,"passed_time":0.3661960677,"remaining_time":0.6653421512},
{"learn":[0.4297099535],"iteration":355,"passed_time":0.3672402873,"remaining_time":0.6643335534},
{"learn":[0.4292861472],"iteration":356,"passed_time":0.3682716764,"remaining_time":0.6633016469},
{"learn":[0.4287428612],"iteration":357,"passed_time":0.3694175207,"remaining_time":0.6624749953},
{"learn":[0.4277973936],"iteration":358,"passed_time":0.3704575068,"remaining_time":0.6614575539},
{"learn":[0.4269707499],"iteration":359,"passed_time":0.3715082472,"remaining_time":0.6604591062},
{"learn":[0.4258646044],"iteration":360,"passed_time":0.3725524602,"remaining_time":0.6594488145},
{"learn":[0.4252783828],"iteration":361,"passed_time":0.3735435737,"remaining_time":0.6583447514},
{"learn":[0.4246869921],"iteration":362,"passed_time":0.3745806396,"remaining_time":0.6573219488},
{"learn":[0.424202125],"iteration":363,"passed_time":0.3756254877,"remaining_time":0.6563126654},
{"learn":[0.423931059],"iteration":364,"passed_time":0.3766694283,"remaining_time":0.6553016082},
{"learn":[0.4230425628],"iteration":365,"passed_time":0.377742087,"remaining_time":0.654340118},
{"learn":[0.4222668903],"iteration":366,"passed_time":0.378783756,"remaining_time":0.6533245709},
{"learn":[0.4218482458],"iteration":367,"passed_time":0.3798333196,"remaining_time":0.6523224401},
{"learn":[0.4209989307],"iteration":368,"passed_time":0.3808648965,"remaining_time":0.6512892946},
{"learn":[0.4205681434],"iteration":369,"passed_time":0.3818767785,"remaining_time":0.6502226229},
{"learn":[0.4197901461],"iteration":370,"passed_time":0.3828873756,"remaining_time":0.6491540681},
{"learn":[0.4191326915],"iteration":371,"passed_time":0.3839161695,"remaining_time":0.6481165441},
{"learn":[0.4185674906],"iteration":372,"passed_time":0.3849746699,"remaining_time":0.6471290027},
{"learn":[0.4181217456],"iteration":373,"passed_time":0.3859692114,"remaining_time":0.6460340277},
{"learn":[0.4172877585],"iteration":374,"passed_time":0.3869593606,"remaining_time":0.6449322677},
{"learn":[0.4165938061],"iteration":375,"passed_time":0.3879755607,"remaining_time":0.6438743348},
{"learn":[0.4161966467],"iteration":376,"passed_time":0.3890461187,"remaining_time":0.6429064507},
{"learn":[0.4156038414],"iteration":377,"passed_time":0.3900847763,"remaining_time":0.6418855313},
{"learn":[0.4150110086],"iteration":378,"passed_time":0.3911384272,"remaining_time":0.6408890852},
{"learn":[0.4142726811],"iteration":379,"passed_time":0.3921970732,"remaining_time":0.6399004878},
{"learn":[0.4133752119],"iteration":380,"passed_time":0.3932874468,"remaining_time":0.6389630697},
{"learn":[0.4125336981],"iteration":381,"passed_time":0.3943811608,"remaining_time":0.638030255},
{"learn":[0.4118367157],"iteration":382,"passed_time":0.395417394,"remaining_time":0.6370040003},
{"learn":[0.4113315669],"iteration":383,"passed_time":0.3964214104,"remaining_time":0.6359260125},
{"learn":[0.4102337948],"iteration":384,"passed_time":0.397494467,"remaining_time":0.6349586941},
{"learn":[0.4096851529],"iteration":385,"passed_time":0.3985436152,"remaining_time":0.6339527972},
{"learn":[0.4089887898],"iteration":386,"passed_time":0.3995897803,"remaining_time":0.6329419518},
{"learn":[0.4083431124],"iteration":387,"passed_time":0.4006633466,"remaining_time":0.6319741446},
{"learn":[0.4079063096],"iteration":388,"passed_time":0.4016559413,"remaining_time":0.6308786122},
{"learn":[0.4071390621],"iteration":389,"passed_time":0.402712972,"remaining_time":0.6298843921},
{"learn":[0.4066192086],"iteration":390,"passed_time":0.403739877,"remaining_time":0.6288429287},
{"learn":[0.4058238355],"iteration":391,"passed_time":0.4047962042,"remaining_time":0.6278471739},
{"learn":[0.4052684549],"iteration":392,"passed_time":0.4059087883,"remaining_time":0.6269380013},
{"learn":[0.404770666],"iteration":393,"passed_time":0.4069519711,"remaining_time":0.625921052},
{"learn":[0.4043321681],"iteration":394,"passed_time":0.4080368878,"remaining_time":0.6249678915},
{"learn":[0.4039325035],"iteration":395,"passed_time":0.4090517402,"remaining_time":0.6239071996},
{"learn":[0.4033813419],"iteration":396,"passed_time":0.4100740542,"remaining_time":0.6228580722},
{"learn":[0.4029013149],"iteration":397,"passed_time":0.4110695643,"remaining_time":0.6217685369},
{"learn":[0.4023621679],"iteration":398,"passed_time":0.4121422997,"remaining_time":0.6207957947},
{"learn":[0.4014811297],"iteration":399,"passed_time":0.4132194582,"remaining_time":0.6198291873},
{"learn":[0.4007553293],"iteration":400,"passed_time":0.4142525882,"remaining_time":0.6187962602},
{"learn":[0.4003145497],"iteration":401,"passed_time":0.4152858263,"remaining_time":0.6177634929},
{"learn":[0.3997121081],"iteration":402,"passed_time":0.4163211894,"remaining_time":0.6167338711},
{"learn":[0.398934854],"iteration":403,"passed_time":0.4173675369,"remaining_time":0.6157204257},
{"learn":[0.3981772461],"iteration":404,"passed_time":0.4184040194,"remaining_time":0.6146923248},
{"learn":[0.397557763],"iteration":405,"passed_time":0.4194166955,"remaining_time":0.6136293526},
{"learn":[0.3971612142],"iteration":406,"passed_time":0.4204368399,"remaining_time":0.6125775088},
{"learn":[0.3965622724],"iteration":407,"passed_time":0.4214706994,"remaining_time":0.6115457207},
{"learn":[0.3959219978],"iteration":408,"passed_time":0.4224526865,"remaining_time":0.6104389675},
{"learn":[0.3953362111],"iteration":409,"passed_time":0.4234897258,"remaining_time":0.6094120444},
{"learn":[0.3950744375],"iteration":410,"passed_time":0.4245437451,"remaining_time":0.608409406},
{"learn":[0.3944816465],"iteration":411,"passed_time":0.4255761589,"remaining_time":0.6073756832},
{"learn":[0.3938513379],"iteration":412,"passed_time":0.4266241308,"remaining_time":0.6063640794},
{"learn":[0.3934424372],"iteration":413,"passed_time":0.4276861106,"remaining_time":0.6053721275},
{"learn":[0.3924851551],"iteration":414,"passed_time":0.4287360618,"remaining_time":0.6043628823},
{"learn":[0.3921136708],"iteration":415,"passed_time":0.429801632,"remaining_time":0.603375368},
{"learn":[0.39161999],"iteration":416,"passed_time":0.430818826,"remaining_time":0.6023198455},
{"learn":[0.3906967874],"iteration":417,"passed_time":0.4318817623,"remaining_time":0.6013281953},
{"learn":[0.389948095],"iteration":418,"passed_time":0.4328884839,"remaining_time":0.6002582557},
{"learn":[0.3895911446],"iteration":419,"passed_time":0.4340489659,"remaining_time":0.5994009529},
{"learn":[0.3891107895],"iteration":420,"passed_time":0.435066105,"remaining_time":0.5983450708},
{"learn":[0.3887485933],"iteration":421,"passed_time":0.4358090252,"remaining_time":0.5969137833},
{"learn":[0.3880393937],"iteration":422,"passed_time":0.43689157,"remaining_time":0.595949021},
{"learn":[0.387692172],"iteration":423,"passed_time":0.4379094252,"remaining_time":0.5948958229},
{"learn":[0.3872246617],"iteration":424,"passed_time":0.4389862758,"remaining_time":0.5939226084},
{"learn":[0.3867302957],"iteration":425,"passed_time":0.439992341,"remaining_time":0.5928535299},
{"learn":[0.38618318],"iteration":426,"passed_time":0.4410600488,"remaining_time":0.591867466},
{"learn":[0.3853603363],"iteration":427,"passed_time":0.4421144383,"remaining_time":0.5908632213},
{"learn":[0.3849427363],"iteration":428,"passed_time":0.4428661745,"remaining_time":0.5894559106},
{"learn":[0.3844137257],"iteration":429,"passed_time":0.4436287564,"remaining_time":0.5880660259},
{"learn":[0.3839056819],"iteration":430,"passed_time":0.4443787155,"remaining_time":0.5866623878},
{"learn":[0.3834149095],"iteration":431,"passed_time":0.4451128455,"remaining_time":0.5852409636},
{"learn":[0.382894072],"iteration":432,"passed_time":0.4458523359,"remaining_time":0.5838297331},
{"learn":[0.3824305141],"iteration":433,"passed_time":0.4469242965,"remaining_time":0.5828551886},
{"learn":[0.3817402602],"iteration":434,"passed_time":0.4480497666,"remaining_time":0.5819496969},
{"learn":[0.3813242347],"iteration":435,"passed_time":0.4490968255,"remaining_time":0.580941765},
{"learn":[0.3805758587],"iteration":436,"passed_time":0.4501336244,"remaining_time":0.579920436},
{"learn":[0.3801407174],"iteration":437,"passed_time":0.4511812587,"remaining_time":0.5789129393},
{"learn":[0.3796799887],"iteration":438,"passed_time":0.4522469461,"remaining_time":0.5779283297},
{"learn":[0.379151639],"iteration":439,"passed_time":0.4532730015,"remaining_time":0.576892911},
{"learn":[0.378753515],"iteration":440,"passed_time":0.4543256688,"remaining_time":0.5758912673},
{"learn":[0.37834689],"iteration":441,"passed_time":0.4550556849,"remaining_time":0.5744820637},
{"learn":[0.3779567083],"iteration":442,"passed_time":0.4558028404,"remaining_time":0.5730974765},
{"learn":[0.3772130139],"iteration":443,"passed_time":0.4565297768,"remaining_time":0.5716904412},
{"learn":[0.3767084191],"iteration":444,"passed_time":0.4573514657,"remaining_time":0.570404637},
{"learn":[0.3761366753],"iteration":445,"passed_time":0.458086368,"remaining_time":0.5690131119},
{"learn":[0.3753942837],"iteration":446,"passed_time":0.4591437894,"remaining_time":0.5680235247},
{"learn":[0.3747968015],"iteration":447,"passed_time":0.4602121518,"remaining_time":0.5670471156},
{"learn":[0.3742186605],"iteration":448,"passed_time":0.4613098814,"remaining_time":0.5661063355},
{"learn":[0.3738471926],"iteration":449,"passed_time":0.4623304376,"remaining_time":0.5650705348},
{"learn":[0.3735945864],"iteration":450,"passed_time":0.4633913576,"remaining_time":0.5640839364},
{"learn":[0.3729343992],"iteration":451,"passed_time":0.4644811859,"remaining_time":0.5631320573},
{"learn":[0.3722288819],"iteration":452,"passed_time":0.4655023666,"remaining_time":0.5620966766},
{"learn":[0.3714219152],"iteration":453,"passed_time":0.4665657472,"remaining_time":0.5611121101},
{"learn":[0.3710386256],"iteration":454,"passed_time":0.4675688524,"remaining_time":0.5600549991},
{"learn":[0.3703916808],"iteration":455,"passed_time":0.4685809972,"remaining_time":0.5590089089},
{"learn":[0.3697097136],"iteration":456,"passed_time":0.4696167104,"remaining_time":0.557990971},
{"learn":[0.3692118241],"iteration":457,"passed_time":0.470773137,"remaining_time":0.5571158085},
{"learn":[0.3689660472],"iteration":458,"passed_time":0.4718051228,"remaining_time":0.5560927482},
{"learn":[0.3687958437],"iteration":459,"passed_time":0.4728529618,"remaining_time":0.5550882595},
{"learn":[0.3680220169],"iteration":460,"passed_time":0.4739516225,"remaining_time":0.5541430033},
{"learn":[0.3673282145],"iteration":461,"passed_time":0.4750361087,"remaining_time":0.5531805767},
{"learn":[0.3669556082],"iteration":462,"passed_time":0.4760702574,"remaining_time":0.5521592402},
{"learn":[0.3664593818],"iteration":463,"passed_time":0.4768134649,"remaining_time":0.5508017612},
{"learn":[0.3661735438],"iteration":464,"passed_time":0.4775427008,"remaining_time":0.5494308493},
{"learn":[0.3652941873],"iteration":465,"passed_time":0.4782620494,"remaining_time":0.5480513614},
{"learn":[0.3648151806],"iteration":466,"passed_time":0.4789748946,"remaining_time":0.546667278},
{"learn":[0.3643599511],"iteration":467,"passed_time":0.4797272396,"remaining_time":0.5453309646},
{"learn":[0.3637922218],"iteration":468,"passed_time":0.4804703227,"remaining_time":0.5439866554},
{"learn":[0.3634656619],"iteration":469,"passed_time":0.4812093143,"remaining_time":0.5426402906},
{"learn":[0.3632481387],"iteration":470,"passed_time":0.4822407789,"remaining_time":0.5416249938},
{"learn":[0.3628192393],"iteration":471,"passed_time":0.4833110905,"remaining_time":0.5406530843},
{"learn":[0.3623362701],"iteration":472,"passed_time":0.4843920098,"remaining_time":0.5396925775},
{"learn":[0.3620266068],"iteration":473,"passed_time":0.4854576222,"remaining_time":0.5387145766},
{"learn":[0.3616916645],"iteration":474,"passed_time":0.4865456988,"remaining_time":0.5377610355},
{"learn":[0.3610937615],"iteration":475,"passed_time":0.4875710677,"remaining_time":0.536737898},
{"learn":[0.3606178245],"iteration":476,"passed_time":0.4885950084,"remaining_time":0.5357131853},
{"learn":[0.3598925056],"iteration":477,"passed_time":0.4896405854,"remaining_time":0.5347121038},
{"learn":[0.3595410569],"iteration":478,"passed_time":0.4907006559,"remaining_time":0.5337266006},
{"learn":[0.3586317228],"iteration":479,"passed_time":0.4916470066,"remaining_time":0.5326175905},
{"learn":[0.3582453665],"iteration":480,"passed_time":0.4926751097,"remaining_time":0.5315974676},
{"learn":[0.3578776911],"iteration":481,"passed_time":0.4937509826,"remaining_time":0.5306286494},
{"learn":[0.3573604977],"iteration":482,"passed_time":0.4948185564,"remaining_time":0.5296505044},
{"learn":[0.3571090182],"iteration":483,"passed_time":0.496156357,"remaining_time":0.5289600831},
{"learn":[0.3566677111],"iteration":484,"passed_time":0.4972297524,"remaining_time":0.527986232},
{"learn":[0.3561435477],"iteration":485,"passed_time":0.4982711901,"remaining_time":0.5269781723},
{"learn":[0.3555691219],"iteration":486,"passed_time":0.4993468481,"remaining_time":0.5260060227},
{"learn":[0.355142732],"iteration":487,"passed_time":0.5004395175,"remaining_time":0.5250512971},
{"learn":[0.3547267317],"iteration":488,"passed_time":0.5015244825,"remaining_time":0.5240879561},
{"learn":[0.3540301655],"iteration":489,"passed_time":0.502689634,"remaining_time":0.5232075783},
{"learn":[0.3537143379],"iteration":490,"passed_time":0.5037315481,"remaining_time":0.5221982851},
{"learn":[0.3535757151],"iteration":491,"passed_time":0.5047180199,"remaining_time":0.5211316141},
{"learn":[0.3528397987],"iteration":492,"passed_time":0.5057892952,"remaining_time":0.5201524801},
{"learn":[0.3520267191],"iteration":493,"passed_time":0.5068826047,"remaining_time":0.5191955425},
{"learn":[0.3514917957],"iteration":494,"passed_time":0.5079527484,"remaining_time":0.5182144201},
{"learn":[0.3506897769],"iteration":495,"passed_time":0.5090187099,"remaining_time":0.5172286891},
{"learn":[0.3504204217],"iteration":496,"passed_time":0.5100602647,"remaining_time":0.5162179339},
{"learn":[0.3497863995],"iteration":497,"passed_time":0.5110777317,"remaining_time":0.5151827737},
{"learn":[0.3493026901],"iteration":498,"passed_time":0.5120551875,"remaining_time":0.5141075129},
{"learn":[0.3490383744],"iteration":499,"passed_time":0.5130856214,"remaining_time":0.5130856214},
{"learn":[0.348687732],"iteration":500,"passed_time":0.5141161905,"remaining_time":0.5120638305},
{"learn":[0.3483382916],"iteration":501,"passed_time":0.5151636256,"remaining_time":0.5110587361},
{"learn":[0.3478434954],"iteration":502,"passed_time":0.5162073609,"remaining_time":0.5100498178},
{"learn":[0.3475762387],"iteration":503,"passed_time":0.5172423362,"remaining_time":0.5090321404},
{"learn":[0.3470810957],"iteration":504,"passed_time":0.5183646186,"remaining_time":0.5080999727},
{"learn":[0.3465851268],"iteration":505,"passed_time":0.5194272167,"remaining_time":0.5071087847},
{"learn":[0.3461345371],"iteration":506,"passed_time":0.5204310701,"remaining_time":0.5060601924},
{"learn":[0.345731589],"iteration":507,"passed_time":0.5215013569,"remaining_time":0.5050761173},
{"learn":[0.3453318676],"iteration":508,"passed_time":0.5225365811,"remaining_time":0.5040578807},
{"learn":[0.3449319881],"iteration":509,"passed_time":0.5235494945,"remaining_time":0.5030181417},
{"learn":[0.3444931383],"iteration":510,"passed_time":0.5246022294,"remaining_time":0.5020166148},
{"learn":[0.3440632832],"iteration":511,"passed_time":0.5256650986,"remaining_time":0.5010245471},
{"learn":[0.3436525646],"iteration":512,"passed_time":0.5267300282,"remaining_time":0.5000341593},
{"learn":[0.343435805],"iteration":513,"passed_time":0.5277346611,"remaining_time":0.4989864694},
{"learn":[0.3431585993],"iteration":514,"passed_time":0.5287977036,"remaining_time":0.4979939539},
{"learn":[0.3429985407],"iteration":515,"passed_time":0.5298743634,"remaining_time":0.4970139377},
{"learn":[0.3424391167],"iteration":516,"passed_time":0.5309105482,"remaining_time":0.4959957346},
{"learn":[0.3416290994],"iteration":517,"passed_time":0.5319626902,"remaining_time":0.4949923102},
{"learn":[0.3414287569],"iteration":518,"passed_time":0.5329738597,"remaining_time":0.4939507255},
{"learn":[0.3412167784],"iteration":519,"passed_time":0.534025201,"remaining_time":0.4929463394},
{"learn":[0.3406824114],"iteration":520,"passed_time":0.5350597881,"remaining_time":0.4919263695},
{"learn":[0.340141625],"iteration":521,"passed_time":0.5360928644,"remaining_time":0.4909049601},
{"learn":[0.3398584877],"iteration":522,"passed_time":0.5371104213,"remaining_time":0.4898693518},
{"learn":[0.3396254119],"iteration":523,"passed_time":0.5381597693,"remaining_time":0.4888626912},
{"learn":[0.3392827951],"iteration":524,"passed_time":0.5391897757,"remaining_time":0.4878383685},
{"learn":[0.3388394078],"iteration":525,"passed_time":0.5402335502,"remaining_time":0.4868264312},
{"learn":[0.3384092439],"iteration":526,"passed_time":0.5412837013,"remaining_time":0.4858200963},
{"learn":[0.3380815517],"iteration":527,"passed_time":0.5422853447,"remaining_time":0.4847702323},
{"learn":[0.3375285691],"iteration":528,"passed_time":0.5433510972,"remaining_time":0.483777631},
{"learn":[0.3368833765],"iteration":529,"passed_time":0.5444173685,"remaining_time":0.4827852136},
{"learn":[0.3364997025],"iteration":530,"passed_time":0.5454694531,"remaining_time":0.4817799878},
{"learn":[0.336261868],"iteration":531,"passed_time":0.5465187872,"remaining_time":0.4807721662},
{"learn":[0.3358478237],"iteration":532,"passed_time":0.5475331402,"remaining_time":0.4797335393},
{"learn":[0.3353915906],"iteration":533,"passed_time":0.5485627281,"remaining_time":0.4787082983},
{"learn":[0.3350422551],"iteration":534,"passed_time":0.5496184339,"remaining_time":0.4777057416},
{"learn":[0.3345213859],"iteration":535,"passed_time":0.5506187433,"remaining_time":0.4766550316},
{"learn":[0.3340885361],"iteration":536,"passed_time":0.5516480686,"remaining_time":0.4756295265},
{"learn":[0.3334069987],"iteration":537,"passed_time":0.5526997075,"remaining_time":0.4746231689},
{"learn":[0.3329344698],"iteration":538,"passed_time":0.5537357402,"remaining_time":0.4736032955},
{"learn":[0.3325849584],"iteration":539,"passed_time":0.5547685641,"remaining_time":0.4725806287},
{"learn":[0.3321706515],"iteration":540,"passed_time":0.5558177859,"remaining_time":0.4715718368},
{"learn":[0.3316553376],"iteration":541,"passed_time":0.5568692637,"remaining_time":0.4705648021},
{"learn":[0.3311914598],"iteration":542,"passed_time":0.5579495899,"remaining_time":0.4695818832},
{"learn":[0.3305292539],"iteration":543,"passed_time":0.5586835587,"remaining_time":0.4683082772},
{"learn":[0.3300736458],"iteration":544,"passed_time":0.5593968405,"remaining_time":0.4670193806},
{"learn":[0.3295564299],"iteration":545,"passed_time":0.5604741446,"remaining_time":0.4660352777},
{"learn":[0.3291457896],"iteration":546,"passed_time":0.56151215,"remaining_time":0.4650182888},
{"learn":[0.32840192],"iteration":547,"passed_time":0.5622392755,"remaining_time":0.4637448039},
{"learn":[0.3279940068],"iteration":548,"passed_time":0.5634076401,"remaining_time":0.4628357845},
{"learn":[0.3275867945],"iteration":549,"passed_time":0.564554526,"remaining_time":0.4619082485},
{"learn":[0.3271487234],"iteration":550,"passed_time":0.5652500573,"remaining_time":0.4606121156},
{"learn":[0.326811894],"iteration":551,"passed_time":0.5663252503,"remaining_time":0.4596262901},
{"learn":[0.3263399947],"iteration":552,"passed_time":0.5674548362,"remaining_time":0.4586841081},
{"learn":[0.3257909492],"iteration":553,"passed_time":0.5685291723,"remaining_time":0.4576967705},
{"learn":[0.3251791744],"iteration":554,"passed_time":0.5695908357,"remaining_time":0.4566989583},
{"learn":[0.3248502915],"iteration":555,"passed_time":0.5706697876,"remaining_time":0.4557147225},
{"learn":[0.3242589581],"iteration":556,"passed_time":0.5717204731,"remaining_time":0.4547076653},
{"learn":[0.3237123889],"iteration":557,"passed_time":0.5727856641,"remaining_time":0.4537119418},
{"learn":[0.32338892],"iteration":558,"passed_time":0.57384096,"remaining_time":0.4527081634},
{"learn":[0.3229253097],"iteration":559,"passed_time":0.5749070301,"remaining_time":0.4517126665},
{"learn":[0.3225810905],"iteration":560,"passed_time":0.5759753666,"remaining_time":0.4507186915},
{"learn":[0.3219762107],"iteration":561,"passed_time":0.5770064139,"remaining_time":0.4496953902},
{"learn":[0.3216368908],"iteration":562,"passed_time":0.5780523502,"remaining_time":0.4486836182},
{"learn":[0.321314723],"iteration":563,"passed_time":0.5791356697,"remaining_time":0.4477006241},
{"learn":[0.3207627664],"iteration":564,"passed_time":0.5802106557,"remaining_time":0.4467108588},
{"learn":[0.3204618022],"iteration":565,"passed_time":0.5812630941,"remaining_time":0.4457035033},
{"learn":[0.319956912],"iteration":566,"passed_time":0.5823299076,"remaining_time":0.4447069665},
{"learn":[0.3196467932],"iteration":567,"passed_time":0.5833963468,"remaining_time":0.4437098975},
{"learn":[0.3191882462],"iteration":568,"passed_time":0.5844223961,"remaining_time":0.4426819908},
{"learn":[0.3188396346],"iteration":569,"passed_time":0.5854784208,"remaining_time":0.4416767034},
{"learn":[0.3182942992],"iteration":570,"passed_time":0.5865013677,"remaining_time":0.4406463866},
{"learn":[0.3178437979],"iteration":571,"passed_time":0.5875758125,"remaining_time":0.439654629},
{"learn":[0.3173966945],"iteration":572,"passed_time":0.5886154834,"remaining_time":0.4386366691},
{"learn":[0.3171380076],"iteration":573,"passed_time":0.5896440103,"remaining_time":0.437610363},
{"learn":[0.3167728259],"iteration":574,"passed_time":0.5906950937,"remaining_time":0.4366007215},
{"learn":[0.3164079185],"iteration":575,"passed_time":0.5917341553,"remaining_time":0.4355820865},
{"learn":[0.3161091662],"iteration":576,"passed_time":0.5927492745,"remaining_time":0.4345458287},
{"learn":[0.3157435274],"iteration":577,"passed_time":0.5937848972,"remaining_time":0.4335246136},
{"learn":[0.3155376482],"iteration":578,"passed_time":0.5947873732,"remaining_time":0.4324792472},
{"learn":[0.3149882059],"iteration":579,"passed_time":0.5958218021,"remaining_time":0.4314571671},
{"learn":[0.3146314789],"iteration":580,"passed_time":0.5968781619,"remaining_time":0.4304508603},
{"learn":[0.3142476163],"iteration":581,"passed_time":0.5979217644,"remaining_time":0.4294352191},
{"learn":[0.3139652002],"iteration":582,"passed_time":0.5989554487,"remaining_time":0.4284123879},
{"learn":[0.313792707],"iteration":583,"passed_time":0.6000286781,"remaining_time":0.4274176885},
{"learn":[0.3134897702],"iteration":584,"passed_time":0.6010554653,"remaining_time":0.4263897746},
{"learn":[0.3132340883],"iteration":585,"passed_time":0.6020854584,"remaining_time":0.4253641293},
{"learn":[0.3130065657],"iteration":586,"passed_time":0.6031177086,"remaining_time":0.4243400574},
{"learn":[0.3127961309],"iteration":587,"passed_time":0.604131811,"remaining_time":0.4233032417},
{"learn":[0.312681776],"iteration":588,"passed_time":0.6051749533,"remaining_time":0.4222867671},
{"learn":[0.3125479344],"iteration":589,"passed_time":0.6062106008,"remaining_time":0.4212649938},
{"learn":[0.3121704768],"iteration":590,"passed_time":0.607243566,"remaining_time":0.4202413172},
{"learn":[0.3119458434],"iteration":591,"passed_time":0.6082894509,"remaining_time":0.4192265135},
{"learn":[0.3117086958],"iteration":592,"passed_time":0.6093621616,"remaining_time":0.4182300164},
{"learn":[0.3113364154],"iteration":593,"passed_time":0.6104140771,"remaining_time":0.4172190493},
{"learn":[0.3107922887],"iteration":594,"passed_time":0.6114457422,"remaining_time":0.4161941607},
{"learn":[0.310413341],"iteration":595,"passed_time":0.6125044534,"remaining_time":0.4151875825},
{"learn":[0.3100452085],"iteration":596,"passed_time":0.6135868967,"remaining_time":0.4141968499},
{"learn":[0.3098543379],"iteration":597,"passed_time":0.6145885424,"remaining_time":0.4131514951},
{"learn":[0.3094868859],"iteration":598,"passed_time":0.6155915993,"remaining_time":0.4121072309},
{"learn":[0.3093360814],"iteration":599,"passed_time":0.616687038,"remaining_time":0.411124692},
{"learn":[0.3091841952],"iteration":600,"passed_time":0.6177413375,"remaining_time":0.4101144653},
{"learn":[0.3088403908],"iteration":601,"passed_time":0.6187749868,"remaining_time":0.4090904398},
{"learn":[0.308575054],"iteration":602,"passed_time":0.6198042196,"remaining_time":0.4080634746},
{"learn":[0.3083089642],"iteration":603,"passed_time":0.6208630552,"remaining_time":0.4070559104},
{"learn":[0.3077989395],"iteration":604,"passed_time":0.6222662495,"remaining_time":0.4062730059},
{"learn":[0.3075408983],"iteration":605,"passed_time":0.6233062307,"remaining_time":0.4052519058},
{"learn":[0.307196072],"iteration":606,"passed_time":0.6243964093,"remaining_time":0.4042632436},
{"learn":[0.3069257551],"iteration":607,"passed_time":0.625407106,"remaining_time":0.4032230025},
{"learn":[0.3063822096],"iteration":608,"passed_time":0.6264568574,"remaining_time":0.4022079331},
{"learn":[0.3058914001],"iteration":609,"passed_time":0.6274946653,"remaining_time":0.4011851139},
{"learn":[0.3054093533],"iteration":610,"passed_time":0.6285713281,"remaining_time":0.400186983},
{"learn":[0.3052381183],"iteration":611,"passed_time":0.6295896,"remaining_time":0.3991515765},
{"learn":[0.3049306565],"iteration":612,"passed_time":0.6305779365,"remaining_time":0.3980973269},
{"learn":[0.3046997011],"iteration":613,"passed_time":0.6316151901,"remaining_time":0.3970740446},
{"learn":[0.3045159523],"iteration":614,"passed_time":0.6326471674,"remaining_time":0.3960474138},
{"learn":[0.3041056352],"iteration":615,"passed_time":0.6337048774,"remaining_time":0.3950368067},
{"learn":[0.3035964239],"iteration":616,"passed_time":0.6347008815,"remaining_time":0.3939877433},
{"learn":[0.3032813889],"iteration":617,"passed_time":0.6357471632,"remaining_time":0.3929699293},
{"learn":[0.3028072341],"iteration":618,"passed_time":0.636803654,"remaining_time":0.3919583072},
{"learn":[0.3026379598],"iteration":619,"passed_time":0.6378340214,"remaining_time":0.3909305293},
{"learn":[0.302136552],"iteration":620,"passed_time":0.6388570263,"remaining_time":0.3898982495},
{"learn":[0.3015692603],"iteration":621,"passed_time":0.6398931586,"remaining_time":0.3888739774},
{"learn":[0.3011410069],"iteration":622,"passed_time":0.6409438465,"remaining_time":0.3878584753},
{"learn":[0.3008177931],"iteration":623,"passed_time":0.6419766269,"remaining_time":0.3868320701},
{"learn":[0.3002790181],"iteration":624,"passed_time":0.6429882584,"remaining_time":0.385792955},
{"learn":[0.3000289053],"iteration":625,"passed_time":0.6440178046,"remaining_time":0.3847646309},
{"learn":[0.2995651689],"iteration":626,"passed_time":0.6450743576,"remaining_time":0.3837523691},
{"learn":[0.2992672001],"iteration":627,"passed_time":0.6460665134,"remaining_time":0.38270182},
{"learn":[0.2989236191],"iteration":628,"passed_time":0.6471455746,"remaining_time":0.3817027157},
{"learn":[0.2986242954],"iteration":629,"passed_time":0.6481888057,"remaining_time":0.3806823145},
{"learn":[0.298053367],"iteration":630,"passed_time":0.6491762074,"remaining_time":0.3796291926},
{"learn":[0.2976629045],"iteration":631,"passed_time":0.6502072989,"remaining_time":0.3786017183},
{"learn":[0.2972185014],"iteration":632,"passed_time":0.6512083353,"remaining_time":0.3775568074},
{"learn":[0.2969883022],"iteration":633,"passed_time":0.6522782453,"remaining_time":0.3765517946},
{"learn":[0.2964005726],"iteration":634,"passed_time":0.6532898514,"remaining_time":0.3755130642},
{"learn":[0.2961745588],"iteration":635,"passed_time":0.6542727618,"remaining_time":0.3744579957},
{"learn":[0.2958457855],"iteration":636,"passed_time":0.6553348726,"remaining_time":0.3734482869},
{"learn":[0.2954739816],"iteration":637,"passed_time":0.6563770518,"remaining_time":0.3724271046},
{"learn":[0.2952229401],"iteration":638,"passed_time":0.6573834787,"remaining_time":0.3713856585},
{"learn":[0.2948799061],"iteration":639,"passed_time":0.6584235444,"remaining_time":0.3703632438},
{"learn":[0.2944794075],"iteration":640,"passed_time":0.6594732276,"remaining_time":0.3693461602},
{"learn":[0.2941142244],"iteration":641,"passed_time":0.6604699176,"remaining_time":0.3682994244},
{"learn":[0.2938879558],"iteration":642,"passed_time":0.6615302923,"remaining_time":0.3672882027},
{"learn":[0.293650104],"iteration":643,"passed_time":0.6626371502,"remaining_time":0.366302524},
{"learn":[0.2935032907],"iteration":644,"passed_time":0.6636875096,"remaining_time":0.3652853735},
{"learn":[0.2930670491],"iteration":645,"passed_time":0.6647223383,"remaining_time":0.3642596095},
{"learn":[0.292540624],"iteration":646,"passed_time":0.6657613165,"remaining_time":0.3632360815},
{"learn":[0.2922711485],"iteration":647,"passed_time":0.6668062033,"remaining_time":0.3622157154},
{"learn":[0.2921295952],"iteration":648,"passed_time":0.6678494338,"remaining_time":0.3611943779},
{"learn":[0.2919022881],"iteration":649,"passed_time":0.6688892526,"remaining_time":0.360171136},
{"learn":[0.2913884727],"iteration":650,"passed_time":0.669947372,"remaining_time":0.3591576541},
{"learn":[0.2911766599],"iteration":651,"passed_time":0.6709971668,"remaining_time":0.3581395921},
{"learn":[0.290821157],"iteration":652,"passed_time":0.6720243532,"remaining_time":0.357109419},
{"learn":[0.2902597618],"iteration":653,"passed_time":0.6730470845,"remaining_time":0.3560768979},
{"learn":[0.2900209528],"iteration":654,"passed_time":0.6740779912,"remaining_time":0.3550487129},
{"learn":[0.2895306214],"iteration":655,"passed_time":0.6750599076,"remaining_time":0.3539948296},
{"learn":[0.2891750413],"iteration":656,"passed_time":0.676142264,"remaining_time":0.3529936021},
{"learn":[0.2889358385],"iteration":657,"passed_time":0.6771768016,"remaining_time":0.3519672738},
{"learn":[0.2886800839],"iteration":658,"passed_time":0.6782419624,"remaining_time":0.3509567666},
{"learn":[0.2882156483],"iteration":659,"passed_time":0.6792814346,"remaining_time":0.3499328602},
{"learn":[0.2879385602],"iteration":660,"passed_time":0.680325799,"remaining_time":0.3489114159},
{"learn":[0.2876868435],"iteration":661,"passed_time":0.6814182686,"remaining_time":0.3479144634},
{"learn":[0.2873927642],"iteration":662,"passed_time":0.682473629,"remaining_time":0.3468983605},
{"learn":[0.2871270223],"iteration":663,"passed_time":0.6835135154,"remaining_time":0.345874309},
{"learn":[0.2869921945],"iteration":664,"passed_time":0.6845492438,"remaining_time":0.3448481153},
{"learn":[0.2864404303],"iteration":665,"passed_time":0.6856177831,"remaining_time":0.3438383477},
{"learn":[0.2863056826],"iteration":666,"passed_time":0.6866578941,"remaining_time":0.342814211},
{"learn":[0.2860144869],"iteration":667,"passed_time":0.6877032024,"remaining_time":0.3417926096},
{"learn":[0.2857592927],"iteration":668,"passed_time":0.6887608533,"remaining_time":0.340777044},
{"learn":[0.2855268445],"iteration":669,"passed_time":0.6898510548,"remaining_time":0.3397773852},
{"learn":[0.2853472441],"iteration":670,"passed_time":0.6908866116,"remaining_time":0.3387506635},
{"learn":[0.2849825726],"iteration":671,"passed_time":0.6919292546,"remaining_time":0.3377273743},
{"learn":[0.2846596912],"iteration":672,"passed_time":0.6930129865,"remaining_time":0.336723992},
{"learn":[0.2842243512],"iteration":673,"passed_time":0.694104566,"remaining_time":0.3357241669},
{"learn":[0.2839984654],"iteration":674,"passed_time":0.6951402587,"remaining_time":0.3346971616},
{"learn":[0.2835447364],"iteration":675,"passed_time":0.696183936,"remaining_time":0.3336739575},
{"learn":[0.2832012851],"iteration":676,"passed_time":0.6971615048,"remaining_time":0.3326191522},
{"learn":[0.2827595559],"iteration":677,"passed_time":0.6981931947,"remaining_time":0.3315902783},
{"learn":[0.2826795775],"iteration":678,"passed_time":0.699267494,"remaining_time":0.3305815399},
{"learn":[0.2825791993],"iteration":679,"passed_time":0.7003344597,"remaining_time":0.3295691575},
{"learn":[0.2822100521],"iteration":680,"passed_time":0.7013811212,"remaining_time":0.3285471038},
{"learn":[0.2819876259],"iteration":681,"passed_time":0.7023814976,"remaining_time":0.3275033963},
{"learn":[0.2816927274],"iteration":682,"passed_time":0.7033962051,"remaining_time":0.3264664671},
{"learn":[0.2813117779],"iteration":683,"passed_time":0.7044440821,"remaining_time":0.3254449268},
{"learn":[0.2811200792],"iteration":684,"passed_time":0.7055096318,"remaining_time":0.3244314365},
{"learn":[0.280758172],"iteration":685,"passed_time":0.706554201,"remaining_time":0.3234081911},
{"learn":[0.2804176023],"iteration":686,"passed_time":0.7076309688,"remaining_time":0.3223995535},
{"learn":[0.2800458579],"iteration":687,"passed_time":0.708707436,"remaining_time":0.3213905814},
{"learn":[0.2797460641],"iteration":688,"passed_time":0.7097730822,"remaining_time":0.3203765291},
{"learn":[0.2793088067],"iteration":689,"passed_time":0.7107969572,"remaining_time":0.3193435605},
{"learn":[0.2788880571],"iteration":690,"passed_time":0.7118814959,"remaining_time":0.3183377456},
{"learn":[0.2786400367],"iteration":691,"passed_time":0.7129408815,"remaining_time":0.317320508},
{"learn":[0.2784011451],"iteration":692,"passed_time":0.7139761661,"remaining_time":0.3162924718},
{"learn":[0.2780208508],"iteration":693,"passed_time":0.7149699498,"remaining_time":0.3152461162},
{"learn":[0.2775632773],"iteration":694,"passed_time":0.715996943,"remaining_time":0.3142144858},
{"learn":[0.277325761],"iteration":695,"passed_time":0.7170142928,"remaining_time":0.3131786566},
{"learn":[0.2770141436],"iteration":696,"passed_time":0.7181183452,"remaining_time":0.3121805719},
{"learn":[0.2767174527],"iteration":697,"passed_time":0.7191747557,"remaining_time":0.3111615705},
{"learn":[0.2763527426],"iteration":698,"passed_time":0.7202308782,"remaining_time":0.3101423381},
{"learn":[0.2758650475],"iteration":699,"passed_time":0.7215572724,"remaining_time":0.309238831},
{"learn":[0.2756987608],"iteration":700,"passed_time":0.7225514009,"remaining_time":0.308192395},
{"learn":[0.2752071315],"iteration":701,"passed_time":0.7235793403,"remaining_time":0.3071604607},
{"learn":[0.2747506571],"iteration":702,"passed_time":0.7246330498,"remaining_time":0.306139425},
{"learn":[0.2745515663],"iteration":703,"passed_time":0.7257159672,"remaining_time":0.3051305771},
{"learn":[0.2742875665],"iteration":704,"passed_time":0.726763302,"remaining_time":0.3041066299},
{"learn":[0.2738975506],"iteration":705,"passed_time":0.7278323364,"remaining_time":0.3030916528},
{"learn":[0.2737807513],"iteration":706,"passed_time":0.7288541988,"remaining_time":0.3020569735},
{"learn":[0.2734186728],"iteration":707,"passed_time":0.7298672891,"remaining_time":0.3010187125},
{"learn":[0.273130488],"iteration":708,"passed_time":0.7309361804,"remaining_time":0.3000034253},
{"learn":[0.2728871601],"iteration":709,"passed_time":0.7319813468,"remaining_time":0.2989782966},
{"learn":[0.2726522033],"iteration":710,"passed_time":0.7329775731,"remaining_time":0.2979332189},
{"learn":[0.272291011],"iteration":711,"passed_time":0.7339770722,"remaining_time":0.2968896022},
{"learn":[0.2720116799],"iteration":712,"passed_time":0.7350296465,"remaining_time":0.2958674734},
{"learn":[0.2718788452],"iteration":713,"passed_time":0.7360749705,"remaining_time":0.2948423551},
{"learn":[0.2715842142],"iteration":714,"passed_time":0.7372139582,"remaining_time":0.2938545148},
{"learn":[0.2711236182],"iteration":715,"passed_time":0.7382638037,"remaining_time":0.2928308942},
{"learn":[0.2708980749],"iteration":716,"passed_time":0.739333529,"remaining_time":0.291815047},
{"learn":[0.2706517573],"iteration":717,"passed_time":0.7403456477,"remaining_time":0.2907764243},
{"learn":[0.2704756488],"iteration":718,"passed_time":0.7413821671,"remaining_time":0.2897474116},
{"learn":[0.270033063],"iteration":719,"passed_time":0.7424107659,"remaining_time":0.2887152979},
{"learn":[0.2697326276],"iteration":720,"passed_time":0.7434284925,"remaining_time":0.2876789867},
{"learn":[0.269474893],"iteration":721,"passed_time":0.7444590484,"remaining_time":0.2866476668},
{"learn":[0.2690881923],"iteration":722,"passed_time":0.7454936439,"remaining_time":0.2856178968},
{"learn":[0.2686847906],"iteration":723,"passed_time":0.746512248,"remaining_time":0.2845820172},
{"learn":[0.2685594736],"iteration":724,"passed_time":0.7475019129,"remaining_time":0.2835352083},
{"learn":[0.2682415016],"iteration":725,"passed_time":0.7485883253,"remaining_time":0.2825250704},
{"learn":[0.2679960175],"iteration":726,"passed_time":0.7496805931,"remaining_time":0.2815169215},
{"learn":[0.2676858332],"iteration":727,"passed_time":0.7507292793,"remaining_time":0.2804922582},
{"learn":[0.2671618372],"iteration":728,"passed_time":0.7517978681,"remaining_time":0.2794749277},
{"learn":[0.2669105723],"iteration":729,"passed_time":0.7528401318,"remaining_time":0.27844772},
{"learn":[0.2667041133],"iteration":730,"passed_time":0.7539012071,"remaining_time":0.2774273936},
{"learn":[0.2662956921],"iteration":731,"passed_time":0.7549130716,"remaining_time":0.2763889388},
{"learn":[0.2659933567],"iteration":732,"passed_time":0.7559557574,"remaining_time":0.2753617834},
{"learn":[0.2656872448],"iteration":733,"passed_time":0.7569889043,"remaining_time":0.2743311288},
{"learn":[0.2655285224],"iteration":734,"passed_time":0.7579962322,"remaining_time":0.2732911586},
{"learn":[0.2652680252],"iteration":735,"passed_time":0.7590449613,"remaining_time":0.2722661274},
{"learn":[0.2648828535],"iteration":736,"passed_time":0.7600926397,"remaining_time":0.271240657},
{"learn":[0.2646047654],"iteration":737,"passed_time":0.7611361401,"remaining_time":0.2702136432},
{"learn":[0.264462605],"iteration":738,"passed_time":0.7622018516,"remaining_time":0.2691944293},
{"learn":[0.2641796696],"iteration":739,"passed_time":0.7632286618,"remaining_time":0.2681614217},
{"learn":[0.263908904],"iteration":740,"passed_time":0.7642276784,"remaining_time":0.2671187162},
{"learn":[0.2636081388],"iteration":741,"passed_time":0.765233048,"remaining_time":0.2660783374},
{"learn":[0.2631580092],"iteration":742,"passed_time":0.7662864677,"remaining_time":0.2650546732},
{"learn":[0.2627374472],"iteration":743,"passed_time":0.7673248385,"remaining_time":0.2640257509},
{"learn":[0.2623854726],"iteration":744,"passed_time":0.7683211843,"remaining_time":0.2629824188},
{"learn":[0.261968133],"iteration":745,"passed_time":0.7693596021,"remaining_time":0.2619535375},
{"learn":[0.261774378],"iteration":746,"passed_time":0.7703781711,"remaining_time":0.260917908},
{"learn":[0.2615706227],"iteration":747,"passed_time":0.7713485983,"remaining_time":0.2598661053},
{"learn":[0.2613217448],"iteration":748,"passed_time":0.7723942151,"remaining_time":0.2588397169},
{"learn":[0.2611914363],"iteration":749,"passed_time":0.7734409751,"remaining_time":0.2578136584},
{"learn":[0.260945557],"iteration":750,"passed_time":0.7744422494,"remaining_time":0.2567724635},
{"learn":[0.2605054508],"iteration":751,"passed_time":0.7754407123,"remaining_time":0.2557304477},
{"learn":[0.2599750141],"iteration":752,"passed_time":0.7764898961,"remaining_time":0.254705185},
{"learn":[0.259840618],"iteration":753,"passed_time":0.7775685267,"remaining_time":0.2536894663},
{"learn":[0.2596763335],"iteration":754,"passed_time":0.7789637534,"remaining_time":0.2527763173},
{"learn":[0.2595179551],"iteration":755,"passed_time":0.7800073595,"remaining_time":0.251748407},
{"learn":[0.2591326887],"iteration":756,"passed_time":0.781059028,"remaining_time":0.2507230433},
{"learn":[0.2588285993],"iteration":757,"passed_time":0.7821228996,"remaining_time":0.2497015062},
{"learn":[0.258624683],"iteration":758,"passed_time":0.7831663028,"remaining_time":0.2486733583},
{"learn":[0.2582748508],"iteration":759,"passed_time":0.7841814088,"remaining_time":0.2476362343},
{"learn":[0.2580803017],"iteration":760,"passed_time":0.7851811814,"remaining_time":0.2465943526},
{"learn":[0.2576727765],"iteration":761,"passed_time":0.7861942488,"remaining_time":0.2455567339},
{"learn":[0.2575686736],"iteration":762,"passed_time":0.7872556639,"remaining_time":0.2445341971},
{"learn":[0.2573491573],"iteration":763,"passed_time":0.7882857119,"remaining_time":0.2435018691},
{"learn":[0.2571308123],"iteration":764,"passed_time":0.7892858632,"remaining_time":0.2424603632},
{"learn":[0.2568314079],"iteration":765,"passed_time":0.7903997588,"remaining_time":0.2414537122},
{"learn":[0.2564713482],"iteration":766,"passed_time":0.7914551935,"remaining_time":0.2404290223},
{"learn":[0.2560718632],"iteration":767,"passed_time":0.7925016491,"remaining_time":0.2394015398},
{"learn":[0.2559360644],"iteration":768,"passed_time":0.7934910435,"remaining_time":0.2383568674},
{"learn":[0.2556005677],"iteration":769,"passed_time":0.794556807,"remaining_time":0.2373351501},
{"learn":[0.2552770606],"iteration":770,"passed_time":0.7955976927,"remaining_time":0.2363059295},
{"learn":[0.2548868694],"iteration":771,"passed_time":0.7966109431,"remaining_time":0.2352685169},
{"learn":[0.2545649988],"iteration":772,"passed_time":0.797675314,"remaining_time":0.2342461789},
{"learn":[0.2542490147],"iteration":773,"passed_time":0.7986308812,"remaining_time":0.2331919627},
{"learn":[0.2538666698],"iteration":774,"passed_time":0.7996685588,"remaining_time":0.2321618396},
{"learn":[0.2536298716],"iteration":775,"passed_time":0.8007309806,"remaining_time":0.2311388397},
{"learn":[0.2534286295],"iteration":776,"passed_time":0.8017560741,"remaining_time":0.2301050251},
{"learn":[0.2531988687],"iteration":777,"passed_time":0.8028366153,"remaining_time":0.2290870548},
{"learn":[0.2530289715],"iteration":778,"passed_time":0.8038831204,"remaining_time":0.2280592678},
{"learn":[0.2527420636],"iteration":779,"passed_time":0.8048761644,"remaining_time":0.2270163541},
{"learn":[0.2526053689],"iteration":780,"passed_time":0.8062248898,"remaining_time":0.2260733046},
{"learn":[0.25232373],"iteration":781,"passed_time":0.8072655371,"remaining_time":0.2250433339},
{"learn":[0.2521919968],"iteration":782,"passed_time":0.808252975,"remaining_time":0.2239985895},
{"learn":[0.2518150138],"iteration":783,"passed_time":0.8092756332,"remaining_time":0.2229636949},
{"learn":[0.2515847557],"iteration":784,"passed_time":0.8102856379,"remaining_time":0.2219253658},
{"learn":[0.2512368498],"iteration":785,"passed_time":0.8113253082,"remaining_time":0.2208951857},
{"learn":[0.2510958099],"iteration":786,"passed_time":0.8123781403,"remaining_time":0.2198685437},
{"learn":[0.2508915985],"iteration":787,"passed_time":0.8133626925,"remaining_time":0.2188234655},
{"learn":[0.2505488308],"iteration":788,"passed_time":0.8143707371,"remaining_time":0.2177848232},
{"learn":[0.2503414698],"iteration":789,"passed_time":0.815429877,"remaining_time":0.2167598407},
{"learn":[0.2499406897],"iteration":790,"passed_time":0.8164561384,"remaining_time":0.2157260846},
{"learn":[0.2496670972],"iteration":791,"passed_time":0.8174719689,"remaining_time":0.214689608},
{"learn":[0.249474909],"iteration":792,"passed_time":0.8185046129,"remaining_time":0.2136575723},
{"learn":[0.2491121589],"iteration":793,"passed_time":0.8195637389,"remaining_time":0.2126324058},
{"learn":[0.2490468915],"iteration":794,"passed_time":0.8206277542,"remaining_time":0.2116084146},
{"learn":[0.2488925016],"iteration":795,"passed_time":0.8216846363,"remaining_time":0.2105824947},
{"learn":[0.2487282924],"iteration":796,"passed_time":0.8227229467,"remaining_time":0.2095517669},
{"learn":[0.2483593865],"iteration":797,"passed_time":0.8237769008,"remaining_time":0.2085249799},
{"learn":[0.2482356763],"iteration":798,"passed_time":0.824811128,"remaining_time":0.2074931624},
{"learn":[0.2478664524],"iteration":799,"passed_time":0.8258751645,"remaining_time":0.2064687911},
{"learn":[0.2475225176],"iteration":800,"passed_time":0.826889797,"remaining_time":0.2054320469},
{"learn":[0.2472349986],"iteration":801,"passed_time":0.8279420767,"remaining_time":0.2044046523},
{"learn":[0.2469922596],"iteration":802,"passed_time":0.8289617857,"remaining_time":0.2033692052},
{"learn":[0.2468068636],"iteration":803,"passed_time":0.82998302,"remaining_time":0.2023341691},
{"learn":[0.2467469751],"iteration":804,"passed_time":0.8309839732,"remaining_time":0.2012942544},
{"learn":[0.2465335509],"iteration":805,"passed_time":0.8319659234,"remaining_time":0.2002498625},
{"learn":[0.2463244403],"iteration":806,"passed_time":0.8329898593,"remaining_time":0.1992156665},
{"learn":[0.2460900968],"iteration":807,"passed_time":0.8341201915,"remaining_time":0.1982067782},
{"learn":[0.2458496985],"iteration":808,"passed_time":0.835211806,"remaining_time":0.1971884486},
{"learn":[0.2456044761],"iteration":809,"passed_time":0.8361859383,"remaining_time":0.1961423806},
{"learn":[0.2452891946],"iteration":810,"passed_time":0.837184775,"remaining_time":0.1951022472},
{"learn":[0.2450457615],"iteration":811,"passed_time":0.8382336158,"remaining_time":0.1940737928},
{"learn":[0.2447233761],"iteration":812,"passed_time":0.8392880922,"remaining_time":0.1930465845},
{"learn":[0.2444846504],"iteration":813,"passed_time":0.8403091357,"remaining_time":0.1920116698},
{"learn":[0.2442190149],"iteration":814,"passed_time":0.8414200194,"remaining_time":0.1909971823},
{"learn":[0.2438390795],"iteration":815,"passed_time":0.8424508923,"remaining_time":0.1899644169},
{"learn":[0.243589715],"iteration":816,"passed_time":0.8434974964,"remaining_time":0.1889351797},
{"learn":[0.2432294894],"iteration":817,"passed_time":0.8447624847,"remaining_time":0.1879544893},
{"learn":[0.2429098514],"iteration":818,"passed_time":0.8458053879,"remaining_time":0.1869240235},
{"learn":[0.2427719499],"iteration":819,"passed_time":0.8468667469,"remaining_time":0.1858975786},
{"learn":[0.2425370536],"iteration":820,"passed_time":0.8479244726,"remaining_time":0.1848702565},
{"learn":[0.2423567676],"iteration":821,"passed_time":0.8489580489,"remaining_time":0.183837631},
{"learn":[0.2422654537],"iteration":822,"passed_time":0.849984722,"remaining_time":0.1828035186},
{"learn":[0.2419447898],"iteration":823,"passed_time":0.8509747963,"remaining_time":0.181761607},
{"learn":[0.2417469934],"iteration":824,"passed_time":0.8520076268,"remaining_time":0.1807288905},
{"learn":[0.2414568547],"iteration":825,"passed_time":0.8530603497,"remaining_time":0.1797003642},
{"learn":[0.2412640044],"iteration":826,"passed_time":0.8540518672,"remaining_time":0.1786589758},
{"learn":[0.2408428522],"iteration":827,"passed_time":0.8550833077,"remaining_time":0.1776260011},
{"learn":[0.2406171457],"iteration":828,"passed_time":0.8561279608,"remaining_time":0.1765957555},
{"learn":[0.2404225695],"iteration":829,"passed_time":0.8571954832,"remaining_time":0.1755701592},
{"learn":[0.2402598404],"iteration":830,"passed_time":0.8582346426,"remaining_time":0.1745386939},
{"learn":[0.2399892077],"iteration":831,"passed_time":0.8592823349,"remaining_time":0.173508933},
{"learn":[0.2397758262],"iteration":832,"passed_time":0.8603499527,"remaining_time":0.1724831238},
{"learn":[0.2396430824],"iteration":833,"passed_time":0.8613852662,"remaining_time":0.1714507844},
{"learn":[0.2393751614],"iteration":834,"passed_time":0.8624120608,"remaining_time":0.1704167545},
{"learn":[0.2388648862],"iteration":835,"passed_time":0.8635202972,"remaining_time":0.1693987186},
{"learn":[0.2385836716],"iteration":836,"passed_time":0.8645413468,"remaining_time":0.1683634881},
{"learn":[0.2383285106],"iteration":837,"passed_time":0.8655872813,"remaining_time":0.1673331021},
{"learn":[0.2381786427],"iteration":838,"passed_time":0.8666103929,"remaining_time":0.1662982995},
{"learn":[0.2377764693],"iteration":839,"passed_time":0.8676160723,"remaining_time":0.1652602043},
{"learn":[0.237636505],"iteration":840,"passed_time":0.8686820936,"remaining_time":0.1642335944},
{"learn":[0.2373499756],"iteration":841,"passed_time":0.8697296023,"remaining_time":0.1632034171},
{"learn":[0.2371278818],"iteration":842,"passed_time":0.8707347298,"remaining_time":0.1621653055},
{"learn":[0.2368516961],"iteration":843,"passed_time":0.8718325874,"remaining_time":0.1611444119},
{"learn":[0.2365253878],"iteration":844,"passed_time":0.8728324367,"remaining_time":0.1601053582},
{"learn":[0.2364668998],"iteration":845,"passed_time":0.87384275,"remaining_time":0.159068302},
{"learn":[0.2362990308],"iteration":846,"passed_time":0.8748904585,"remaining_time":0.1580380639},
{"learn":[0.2361402987],"iteration":847,"passed_time":0.8759442013,"remaining_time":0.1570088663},
{"learn":[0.2359075642],"iteration":848,"passed_time":0.8770260408,"remaining_time":0.155984608},
{"learn":[0.2358441957],"iteration":849,"passed_time":0.8780247072,"remaining_time":0.1549455366},
{"learn":[0.2356601235],"iteration":850,"passed_time":0.8790819256,"remaining_time":0.1539168119},
{"learn":[0.2354358092],"iteration":851,"passed_time":0.8801310671,"remaining_time":0.1528866173},
{"learn":[0.235099853],"iteration":852,"passed_time":0.8811321525,"remaining_time":0.1518480966},
{"learn":[0.234895399],"iteration":853,"passed_time":0.8821596837,"remaining_time":0.1508141848},
{"learn":[0.2345264282],"iteration":854,"passed_time":0.8832411971,"remaining_time":0.1497894428},
{"learn":[0.2344317497],"iteration":855,"passed_time":0.8842906478,"remaining_time":0.1487591744},
{"learn":[0.2341285549],"iteration":856,"passed_time":0.88535937,"remaining_time":0.1477320769},
{"learn":[0.233945505],"iteration":857,"passed_time":0.8864015595,"remaining_time":0.1467004912},
{"learn":[0.2338522238],"iteration":858,"passed_time":0.8874786214,"remaining_time":0.1456746049},
{"learn":[0.2336526404],"iteration":859,"passed_time":0.8885079309,"remaining_time":0.144640826},
{"learn":[0.2335481166],"iteration":860,"passed_time":0.8895789025,"remaining_time":0.1436137833},
{"learn":[0.2331191467],"iteration":861,"passed_time":0.8906194103,"remaining_time":0.1425817617},
{"learn":[0.2329052454],"iteration":862,"passed_time":0.891813731,"remaining_time":0.1415741381},
{"learn":[0.2326404295],"iteration":863,"passed_time":0.892873145,"remaining_time":0.1405448469},
{"learn":[0.2322620179],"iteration":864,"passed_time":0.8939391856,"remaining_time":0.1395165203},
{"learn":[0.2321663472],"iteration":865,"passed_time":0.8949537674,"remaining_time":0.1384801442},
{"learn":[0.2318794355],"iteration":866,"passed_time":0.8959802486,"remaining_time":0.1374456437},
{"learn":[0.231758479],"iteration":867,"passed_time":0.8970537442,"remaining_time":0.1364183113},
{"learn":[0.2315116103],"iteration":868,"passed_time":0.8980247643,"remaining_time":0.1353754248},
{"learn":[0.231317435],"iteration":869,"passed_time":0.8990224971,"remaining_time":0.134336695},
{"learn":[0.2312383865],"iteration":870,"passed_time":0.9000691616,"remaining_time":0.1333053064},
{"learn":[0.230927253],"iteration":871,"passed_time":0.9011248922,"remaining_time":0.1322752135},
{"learn":[0.2308012889],"iteration":872,"passed_time":0.9021199525,"remaining_time":0.1312362359},
{"learn":[0.2306071323],"iteration":873,"passed_time":0.9031931969,"remaining_time":0.1302086302},
{"learn":[0.2304062227],"iteration":874,"passed_time":0.9042826418,"remaining_time":0.1291832345},
{"learn":[0.2301520542],"iteration":875,"passed_time":0.9053284211,"remaining_time":0.1281515117},
{"learn":[0.2299379927],"iteration":876,"passed_time":0.9063792515,"remaining_time":0.1271204652},
{"learn":[0.2298533616],"iteration":877,"passed_time":0.9073766444,"remaining_time":0.1260819483},
{"learn":[0.2296699073],"iteration":878,"passed_time":0.908421091,"remaining_time":0.1250500023},
{"learn":[0.2295104319],"iteration":879,"passed_time":0.9094635341,"remaining_time":0.1240177546},
{"learn":[0.2294074659],"iteration":880,"passed_time":0.9105015432,"remaining_time":0.1229848849},
{"learn":[0.2292459641],"iteration":881,"passed_time":0.9114647833,"remaining_time":0.1219420005},
{"learn":[0.2290573545],"iteration":882,"passed_time":0.9125372567,"remaining_time":0.1209137701},
{"learn":[0.2286684155],"iteration":883,"passed_time":0.9135694846,"remaining_time":0.1198801586},
{"learn":[0.2285271531],"iteration":884,"passed_time":0.9145623317,"remaining_time":0.1188414329},
{"learn":[0.2283149038],"iteration":885,"passed_time":0.915614717,"remaining_time":0.1178104715},
{"learn":[0.2281151548],"iteration":886,"passed_time":0.9166347848,"remaining_time":0.1167753446},
{"learn":[0.2279094832],"iteration":887,"passed_time":0.9176947169,"remaining_time":0.1157452796},
{"learn":[0.227674794],"iteration":888,"passed_time":0.918751093,"remaining_time":0.1147147034},
{"learn":[0.2274293853],"iteration":889,"passed_time":0.9197974218,"remaining_time":0.1136828274},
{"learn":[0.2272116392],"iteration":890,"passed_time":0.9207589012,"remaining_time":0.112640539},
{"learn":[0.2270832667],"iteration":891,"passed_time":0.9217947316,"remaining_time":0.1116074339},
{"learn":[0.2269423273],"iteration":892,"passed_time":0.9228525406,"remaining_time":0.1105769562},
{"learn":[0.2268246277],"iteration":893,"passed_time":0.9238726669,"remaining_time":0.1095419493},
{"learn":[0.2266529901],"iteration":894,"passed_time":0.9248801077,"remaining_time":0.1085054875},
{"learn":[0.2264447337],"iteration":895,"passed_time":0.925908872,"remaining_time":0.1074715655},
{"learn":[0.2262134676],"iteration":896,"passed_time":0.92693059,"remaining_time":0.1064368459},
{"learn":[0.2259773725],"iteration":897,"passed_time":0.9279200291,"remaining_time":0.1053984888},
{"learn":[0.2258092193],"iteration":898,"passed_time":0.9289919897,"remaining_time":0.1043695116},
{"learn":[0.2256795142],"iteration":899,"passed_time":0.9300399386,"remaining_time":0.103337771},
{"learn":[0.2254829886],"iteration":900,"passed_time":0.9310894563,"remaining_time":0.1023061667},
{"learn":[0.2252766656],"iteration":901,"passed_time":0.9321355997,"remaining_time":0.1012741561},
{"learn":[0.2250534697],"iteration":902,"passed_time":0.9331196103,"remaining_time":0.1002354399},
{"learn":[0.2246247481],"iteration":903,"passed_time":0.9341662645,"remaining_time":0.09920349712},
{"learn":[0.2244545847],"iteration":904,"passed_time":0.9351739354,"remaining_time":0.09816742968},
{"learn":[0.224235124],"iteration":905,"passed_time":0.9362295543,"remaining_time":0.09713639967},
{"learn":[0.2240620246],"iteration":906,"passed_time":0.9376084591,"remaining_time":0.09613846383},
{"learn":[0.2238423431],"iteration":907,"passed_time":0.9386360917,"remaining_time":0.0951040974},
{"learn":[0.2234823513],"iteration":908,"passed_time":0.939622447,"remaining_time":0.0940656135},
{"learn":[0.2232680979],"iteration":909,"passed_time":0.9407188173,"remaining_time":0.09303812479},
{"learn":[0.2229959465],"iteration":910,"passed_time":0.9417667523,"remaining_time":0.09200575297},
{"learn":[0.2227195898],"iteration":911,"passed_time":0.9428079322,"remaining_time":0.09097269521},
{"learn":[0.2226298656],"iteration":912,"passed_time":0.9438206397,"remaining_time":0.08993690652},
{"learn":[0.2224096516],"iteration":913,"passed_time":0.9448605176,"remaining_time":0.08890372485},
{"learn":[0.2222113545],"iteration":914,"passed_time":0.9458733326,"remaining_time":0.0878680145},
{"learn":[0.2220998159],"iteration":915,"passed_time":0.9468980095,"remaining_time":0.08683344192},
{"learn":[0.2219135605],"iteration":916,"passed_time":0.9479481582,"remaining_time":0.08580119643},
{"learn":[0.2217666211],"iteration":917,"passed_time":0.9489879733,"remaining_time":0.0847679889},
{"learn":[0.2214720932],"iteration":918,"passed_time":0.950030792,"remaining_time":0.08373503172},
{"learn":[0.2212792024],"iteration":919,"passed_time":0.9511594461,"remaining_time":0.08270951705},
{"learn":[0.2209967613],"iteration":920,"passed_time":0.9522169894,"remaining_time":0.08167767879},
{"learn":[0.2207520946],"iteration":921,"passed_time":0.9532652209,"remaining_time":0.080644997},
{"learn":[0.2205031078],"iteration":922,"passed_time":0.9543210409,"remaining_time":0.07961291457},
{"learn":[0.2203972132],"iteration":923,"passed_time":0.9553491162,"remaining_time":0.07857849873},
{"learn":[0.2201738914],"iteration":924,"passed_time":0.9564061891,"remaining_time":0.07754644777},
{"learn":[0.2200383329],"iteration":925,"passed_time":0.9574062703,"remaining_time":0.07650978834},
{"learn":[0.2197823388],"iteration":926,"passed_time":0.9584513401,"remaining_time":0.07547675062},
{"learn":[0.2195850755],"iteration":927,"passed_time":0.9595339779,"remaining_time":0.07444660173},
{"learn":[0.2192961359],"iteration":928,"passed_time":0.9605921498,"remaining_time":0.07341447001},
{"learn":[0.2190523596],"iteration":929,"passed_time":0.9616030488,"remaining_time":0.0723787241},
{"learn":[0.2189433927],"iteration":930,"passed_time":0.9626314206,"remaining_time":0.07134432655},
{"learn":[0.2184984377],"iteration":931,"passed_time":0.9636676072,"remaining_time":0.07031051212},
{"learn":[0.2183517977],"iteration":932,"passed_time":0.9646598511,"remaining_time":0.06927353701},
{"learn":[0.2181594069],"iteration":933,"passed_time":0.9656273798,"remaining_time":0.06823491121},
{"learn":[0.217921696],"iteration":934,"passed_time":0.9666649088,"remaining_time":0.06720130382},
{"learn":[0.2177221766],"iteration":935,"passed_time":0.9676945939,"remaining_time":0.06616715172},
{"learn":[0.2175168627],"iteration":936,"passed_time":0.968746437,"remaining_time":0.06513449897},
{"learn":[0.2173622916],"iteration":937,"passed_time":0.9697683501,"remaining_time":0.06409982698},
{"learn":[0.2172311442],"iteration":938,"passed_time":0.9707935511,"remaining_time":0.06306539576},
{"learn":[0.2170772529],"iteration":939,"passed_time":0.9718330353,"remaining_time":0.06203189587},
{"learn":[0.2168960288],"iteration":940,"passed_time":0.9728617126,"remaining_time":0.06099770568},
{"learn":[0.2167307248],"iteration":941,"passed_time":0.9739083198,"remaining_time":0.05996463115},
{"learn":[0.2166393341],"iteration":942,"passed_time":0.9749642986,"remaining_time":0.0589320944},
{"learn":[0.2163889372],"iteration":943,"passed_time":0.9760058214,"remaining_time":0.05789865042},
{"learn":[0.2162051732],"iteration":944,"passed_time":0.9770539382,"remaining_time":0.05686557312},
{"learn":[0.2159916499],"iteration":945,"passed_time":0.9781293769,"remaining_time":0.05583402363},
{"learn":[0.2157219665],"iteration":946,"passed_time":0.9791695423,"remaining_time":0.05480040733},
{"learn":[0.2153783238],"iteration":947,"passed_time":0.9801922458,"remaining_time":0.05376581939},
{"learn":[0.2151446987],"iteration":948,"passed_time":0.9811719449,"remaining_time":0.05272894541},
{"learn":[0.2150486802],"iteration":949,"passed_time":0.9823362167,"remaining_time":0.05170190614},
{"learn":[0.2148170844],"iteration":950,"passed_time":0.98339631,"remaining_time":0.05066921051},
{"learn":[0.214640631],"iteration":951,"passed_time":0.9844323512,"remaining_time":0.0496352446},
{"learn":[0.2143074382],"iteration":952,"passed_time":0.9854665735,"remaining_time":0.04860118463},
{"learn":[0.2141521939],"iteration":953,"passed_time":0.9865046092,"remaining_time":0.0475673082},
{"learn":[0.2139300032],"iteration":954,"passed_time":0.9873998453,"remaining_time":0.04652669428},
{"learn":[0.2138116895],"iteration":955,"passed_time":0.9884435118,"remaining_time":0.04549321602},
{"learn":[0.213565557],"iteration":956,"passed_time":0.9894221819,"remaining_time":0.04445679605},
{"learn":[0.2134513596],"iteration":957,"passed_time":0.9904654136,"remaining_time":0.04342332711},
{"learn":[0.2132139577],"iteration":958,"passed_time":0.9915237359,"remaining_time":0.04239048298},
{"learn":[0.2131528261],"iteration":959,"passed_time":0.9925622619,"remaining_time":0.04135676091},
{"learn":[0.2129578708],"iteration":960,"passed_time":0.9935590219,"remaining_time":0.04032133388},
{"learn":[0.2126081564],"iteration":961,"passed_time":0.9945862736,"remaining_time":0.03928719168},
{"learn":[0.212485241],"iteration":962,"passed_time":0.9955862515,"remaining_time":0.03825201589},
{"learn":[0.2123441309],"iteration":963,"passed_time":0.9965996226,"remaining_time":0.03721741329},
{"learn":[0.2120419381],"iteration":964,"passed_time":0.9976561986,"remaining_time":0.03618442171},
{"learn":[0.2118779147],"iteration":965,"passed_time":0.9986740122,"remaining_time":0.03515001699},
{"learn":[0.2116754214],"iteration":966,"passed_time":0.9997099319,"remaining_time":0.03411626448},
{"learn":[0.2115492194],"iteration":967,"passed_time":1.000708173,"remaining_time":0.03308126192},
{"learn":[0.2113434394],"iteration":968,"passed_time":1.001718966,"remaining_time":0.03204673678},
{"learn":[0.2112224311],"iteration":969,"passed_time":1.002741253,"remaining_time":0.03101261608},
{"learn":[0.2111038967],"iteration":970,"passed_time":1.003800757,"remaining_time":0.02997963125},
{"learn":[0.2109191674],"iteration":971,"passed_time":1.004827542,"remaining_time":0.02894564935},
{"learn":[0.2107240387],"iteration":972,"passed_time":1.005838,"remaining_time":0.0279112292},
{"learn":[0.2106490569],"iteration":973,"passed_time":1.006822198,"remaining_time":0.02687615722},
{"learn":[0.2103797233],"iteration":974,"passed_time":1.007874007,"remaining_time":0.02584292327},
{"learn":[0.2101238359],"iteration":975,"passed_time":1.008893457,"remaining_time":0.02480885551},
{"learn":[0.2099377111],"iteration":976,"passed_time":1.00992201,"remaining_time":0.02377503197},
{"learn":[0.2098381959],"iteration":977,"passed_time":1.010967801,"remaining_time":0.02274160698},
{"learn":[0.2097122688],"iteration":978,"passed_time":1.012071365,"remaining_time":0.02170939598},
{"learn":[0.2094832807],"iteration":979,"passed_time":1.013145026,"remaining_time":0.0206764291},
{"learn":[0.2092221442],"iteration":980,"passed_time":1.014161099,"remaining_time":0.01964226389},
{"learn":[0.2090387241],"iteration":981,"passed_time":1.015189091,"remaining_time":0.01860835402},
{"learn":[0.208846205],"iteration":982,"passed_time":1.016264857,"remaining_time":0.01757528238},
{"learn":[0.208698014],"iteration":983,"passed_time":1.017232728,"remaining_time":0.01654036957},
{"learn":[0.2085119918],"iteration":984,"passed_time":1.018278285,"remaining_time":0.01550677591},
{"learn":[0.2084214172],"iteration":985,"passed_time":1.019299327,"remaining_time":0.01447280992},
{"learn":[0.2082210786],"iteration":986,"passed_time":1.020319891,"remaining_time":0.01343886381},
{"learn":[0.2080061502],"iteration":987,"passed_time":1.021353436,"remaining_time":0.01240510246},
{"learn":[0.2077477875],"iteration":988,"passed_time":1.022420374,"remaining_time":0.01137171295},
{"learn":[0.2076375769],"iteration":989,"passed_time":1.023450795,"remaining_time":0.01033788682},
{"learn":[0.2074658728],"iteration":990,"passed_time":1.024467567,"remaining_time":0.009303943592},
{"learn":[0.2073266441],"iteration":991,"passed_time":1.02555616,"remaining_time":0.00827061419},
{"learn":[0.2071712947],"iteration":992,"passed_time":1.026591946,"remaining_time":0.00723680123},
{"learn":[0.206872426],"iteration":993,"passed_time":1.027648806,"remaining_time":0.006203111507},
{"learn":[0.2066092843],"iteration":994,"passed_time":1.028751165,"remaining_time":0.005169603844},
{"learn":[0.2064211619],"iteration":995,"passed_time":1.029772724,"remaining_time":0.004135633428},
{"learn":[0.2061352247],"iteration":996,"passed_time":1.030830048,"remaining_time":0.003101795531},
{"learn":[0.2060030917],"iteration":997,"passed_time":1.031883802,"remaining_time":0.002067903412},
{"learn":[0.2058238354],"iteration":998,"passed_time":1.032893221,"remaining_time":0.001033927149},
{"learn":[0.2056767924],"iteration":999,"passed_time":1.033902924,"remaining_time":0}
]}